[{"trial_id": 98286802, "stateRewards": [0.0, -4.0, 1.0, -1.0, -1.0, 1.0, -6.0]}, {"trial_id": 53161791, "stateRewards": [0.0, -1.0, 6.0, -4.0, -1.0, 1.0, -4.0]}, {"trial_id": 66254856, "stateRewards": [0.0, 4.0, 1.0, 6.0, 1.0, 4.0, -4.0]}, {"trial_id": 70498984, "stateRewards": [0.0, -1.0, 1.0, 1.0, -1.0, -1.0, 1.0]}, {"trial_id": 30410125, "stateRewards": [0.0, 4.0, 6.0, 1.0, 4.0, -1.0, -4.0]}, {"trial_id": 31388680, "stateRewards": [0.0, -1.0, -1.0, 1.0, -4.0, 4.0, 4.0]}, {"trial_id": 23623703, "stateRewards": [0.0, 4.0, -4.0, -4.0, 4.0, -1.0, -6.0]}, {"trial_id": 8300053, "stateRewards": [0.0, 6.0, 4.0, 4.0, 4.0, -6.0, 1.0]}, {"trial_id": 3747189, "stateRewards": [0.0, 4.0, 1.0, 4.0, -4.0, 1.0, 1.0]}, {"trial_id": 69643080, "stateRewards": [0.0, 1.0, 4.0, -1.0, 1.0, 1.0, -1.0]}, {"trial_id": 42925130, "stateRewards": [0.0, 1.0, 1.0, 6.0, -4.0, -6.0, -1.0]}, {"trial_id": 90122758, "stateRewards": [0.0, 1.0, -1.0, 1.0, 1.0, 1.0, 4.0]}, {"trial_id": 67992943, "stateRewards": [0.0, 1.0, -4.0, 6.0, -1.0, 6.0, -1.0]}, {"trial_id": 35184220, "stateRewards": [0.0, -1.0, 4.0, 4.0, 6.0, 1.0, 1.0]}, {"trial_id": 96623900, "stateRewards": [0.0, -1.0, -1.0, -1.0, 6.0, 1.0, 4.0]}, {"trial_id": 90055324, "stateRewards": [0.0, 1.0, -4.0, 6.0, -6.0, 1.0, 4.0]}, {"trial_id": 15373216, "stateRewards": [0.0, 4.0, 4.0, 1.0, -6.0, -4.0, -1.0]}, {"trial_id": 39563914, "stateRewards": [0.0, 1.0, -1.0, 1.0, -4.0, -4.0, 4.0]}, {"trial_id": 97894976, "stateRewards": [0.0, 1.0, -4.0, 4.0, 1.0, -1.0, -1.0]}, {"trial_id": 39543121, "stateRewards": [0.0, -6.0, 1.0, 1.0, -1.0, 4.0, 4.0]}, {"trial_id": 42255459, "stateRewards": [0.0, -6.0, -1.0, -4.0, 1.0, -4.0, 1.0]}, {"trial_id": 42712898, "stateRewards": [0.0, -4.0, 1.0, 1.0, 4.0, 1.0, -1.0]}, {"trial_id": 53489059, "stateRewards": [0.0, -1.0, 1.0, 4.0, 1.0, 6.0, 6.0]}, {"trial_id": 2947184, "stateRewards": [0.0, -1.0, -1.0, -4.0, 1.0, -4.0, -4.0]}, {"trial_id": 17811674, "stateRewards": [0.0, -1.0, 4.0, -4.0, -4.0, 1.0, 1.0]}, {"trial_id": 62793768, "stateRewards": [0.0, -4.0, -1.0, -1.0, 1.0, -1.0, 4.0]}, {"trial_id": 1730014, "stateRewards": [0.0, -1.0, -1.0, 4.0, -1.0, -1.0, -1.0]}, {"trial_id": 11633693, "stateRewards": [0.0, 6.0, 4.0, -1.0, 1.0, -1.0, 6.0]}, {"trial_id": 35031465, "stateRewards": [0.0, -1.0, 4.0, 1.0, -4.0, -1.0, 1.0]}, {"trial_id": 34259516, "stateRewards": [0.0, 1.0, 6.0, 4.0, 4.0, -1.0, 1.0]}, {"trial_id": 79741720, "stateRewards": [0.0, 6.0, 6.0, 4.0, -4.0, -1.0, -4.0]}, {"trial_id": 41265234, "stateRewards": [0.0, -4.0, -1.0, 1.0, 4.0, 1.0, 6.0]}, {"trial_id": 72094557, "stateRewards": [0.0, 4.0, 1.0, 4.0, 1.0, -1.0, -4.0]}, {"trial_id": 46291978, "stateRewards": [0.0, 1.0, -1.0, 6.0, 1.0, -1.0, 1.0]}, {"trial_id": 18856543, "stateRewards": [0.0, -1.0, 1.0, -6.0, -1.0, 4.0, 1.0]}, {"trial_id": 382277, "stateRewards": [0.0, 6.0, 4.0, 1.0, 1.0, 1.0, -6.0]}, {"trial_id": 48315114, "stateRewards": [0.0, -6.0, -1.0, 1.0, 1.0, -4.0, 4.0]}, {"trial_id": 95800315, "stateRewards": [0.0, -1.0, -1.0, 4.0, 4.0, -1.0, 4.0]}, {"trial_id": 40172319, "stateRewards": [0.0, 1.0, 1.0, 4.0, 4.0, -6.0, 4.0]}, {"trial_id": 92220544, "stateRewards": [0.0, 6.0, 6.0, 1.0, -4.0, -1.0, -4.0]}, {"trial_id": 47478599, "stateRewards": [0.0, 4.0, -4.0, -1.0, 4.0, -4.0, 1.0]}, {"trial_id": 42713423, "stateRewards": [0.0, -4.0, -1.0, -4.0, -6.0, -1.0, -1.0]}, {"trial_id": 2495768, "stateRewards": [0.0, -1.0, 1.0, 1.0, 1.0, 6.0, 4.0]}, {"trial_id": 29691907, "stateRewards": [0.0, -1.0, 1.0, -4.0, 1.0, -4.0, 4.0]}, {"trial_id": 17264714, "stateRewards": [0.0, 4.0, -6.0, -1.0, 1.0, 1.0, -1.0]}, {"trial_id": 77465853, "stateRewards": [0.0, -1.0, -1.0, -6.0, -1.0, 4.0, -1.0]}, {"trial_id": 53255797, "stateRewards": [0.0, -4.0, -1.0, -1.0, -1.0, 4.0, -1.0]}, {"trial_id": 51306007, "stateRewards": [0.0, -1.0, -6.0, -4.0, 4.0, 4.0, 1.0]}, {"trial_id": 34749307, "stateRewards": [0.0, -1.0, 1.0, 1.0, -4.0, -4.0, -1.0]}, {"trial_id": 3980622, "stateRewards": [0.0, -6.0, 1.0, 4.0, 6.0, 1.0, -1.0]}, {"trial_id": 69851178, "stateRewards": [0.0, 1.0, 4.0, -1.0, -1.0, -1.0, 1.0]}, {"trial_id": 90308764, "stateRewards": [0.0, 4.0, -1.0, -4.0, 4.0, -4.0, -4.0]}, {"trial_id": 43025685, "stateRewards": [0.0, -4.0, -6.0, -1.0, -1.0, 4.0, -1.0]}, {"trial_id": 4278892, "stateRewards": [0.0, 1.0, 1.0, 1.0, -4.0, -1.0, 1.0]}, {"trial_id": 88084224, "stateRewards": [0.0, 4.0, -4.0, 1.0, -4.0, 1.0, 4.0]}, {"trial_id": 93117893, "stateRewards": [0.0, 1.0, -6.0, -4.0, 1.0, 1.0, -1.0]}, {"trial_id": 65344865, "stateRewards": [0.0, -4.0, 1.0, -6.0, -4.0, -1.0, 4.0]}, {"trial_id": 22692904, "stateRewards": [0.0, -1.0, -4.0, 1.0, 1.0, 1.0, -1.0]}, {"trial_id": 32940437, "stateRewards": [0.0, 6.0, -4.0, -1.0, 1.0, -4.0, 1.0]}, {"trial_id": 25061490, "stateRewards": [0.0, -4.0, 6.0, 1.0, 4.0, -4.0, -1.0]}, {"trial_id": 26602356, "stateRewards": [0.0, 4.0, 4.0, 4.0, -4.0, 4.0, 4.0]}, {"trial_id": 29169535, "stateRewards": [0.0, 6.0, 1.0, 4.0, -1.0, 1.0, -6.0]}, {"trial_id": 59464721, "stateRewards": [0.0, 4.0, 1.0, 6.0, 1.0, 4.0, -1.0]}, {"trial_id": 73465774, "stateRewards": [0.0, -4.0, -6.0, -1.0, 4.0, 4.0, 4.0]}, {"trial_id": 93944752, "stateRewards": [0.0, -4.0, -1.0, 4.0, 1.0, -4.0, -6.0]}, {"trial_id": 98392425, "stateRewards": [0.0, 1.0, -4.0, -6.0, 4.0, 1.0, -4.0]}, {"trial_id": 15303228, "stateRewards": [0.0, -1.0, 1.0, -6.0, 1.0, 1.0, -1.0]}, {"trial_id": 7035295, "stateRewards": [0.0, -1.0, -6.0, -4.0, -1.0, 4.0, 4.0]}, {"trial_id": 41988527, "stateRewards": [0.0, 1.0, -1.0, -4.0, -1.0, -4.0, 4.0]}, {"trial_id": 43398764, "stateRewards": [0.0, -1.0, 1.0, 1.0, -4.0, -1.0, -6.0]}, {"trial_id": 87902102, "stateRewards": [0.0, -1.0, -4.0, 6.0, -1.0, 1.0, 1.0]}, {"trial_id": 72402270, "stateRewards": [0.0, 1.0, 1.0, -6.0, -4.0, 1.0, -1.0]}, {"trial_id": 91103699, "stateRewards": [0.0, 1.0, 4.0, 1.0, 1.0, -1.0, -6.0]}, {"trial_id": 92137622, "stateRewards": [0.0, 1.0, 1.0, 4.0, -4.0, -1.0, 1.0]}, {"trial_id": 10013831, "stateRewards": [0.0, -4.0, 1.0, 4.0, -1.0, -1.0, -1.0]}, {"trial_id": 23244044, "stateRewards": [0.0, -1.0, -1.0, -6.0, -1.0, -1.0, 4.0]}, {"trial_id": 92592354, "stateRewards": [0.0, -4.0, 1.0, -1.0, -1.0, -4.0, -1.0]}, {"trial_id": 99599667, "stateRewards": [0.0, -1.0, 4.0, 4.0, 4.0, -1.0, 4.0]}, {"trial_id": 8922142, "stateRewards": [0.0, -4.0, 1.0, 6.0, 6.0, -1.0, 6.0]}, {"trial_id": 40002382, "stateRewards": [0.0, 1.0, -4.0, -1.0, -1.0, 4.0, -1.0]}, {"trial_id": 71452587, "stateRewards": [0.0, 4.0, -4.0, -1.0, -4.0, -4.0, 1.0]}, {"trial_id": 47292037, "stateRewards": [0.0, -1.0, 1.0, 4.0, 1.0, -4.0, 1.0]}, {"trial_id": 76546410, "stateRewards": [0.0, -4.0, -1.0, 1.0, -1.0, -1.0, 1.0]}, {"trial_id": 63909156, "stateRewards": [0.0, -4.0, 1.0, 4.0, 4.0, 4.0, -4.0]}, {"trial_id": 81151369, "stateRewards": [0.0, 1.0, 1.0, -4.0, 1.0, 4.0, -1.0]}, {"trial_id": 26226777, "stateRewards": [0.0, -1.0, 1.0, 4.0, 1.0, 1.0, -1.0]}, {"trial_id": 68452546, "stateRewards": [0.0, -1.0, 1.0, -4.0, 4.0, -1.0, -4.0]}, {"trial_id": 85034213, "stateRewards": [0.0, 1.0, 1.0, -1.0, -4.0, 1.0, 1.0]}, {"trial_id": 30534696, "stateRewards": [0.0, -6.0, -1.0, 1.0, 4.0, 1.0, -1.0]}, {"trial_id": 54632268, "stateRewards": [0.0, -4.0, 4.0, -1.0, -4.0, 4.0, -4.0]}, {"trial_id": 11183034, "stateRewards": [0.0, 1.0, 1.0, -1.0, -1.0, 4.0, -1.0]}, {"trial_id": 52910490, "stateRewards": [0.0, -4.0, 4.0, -1.0, 4.0, 4.0, -4.0]}, {"trial_id": 52568736, "stateRewards": [0.0, -4.0, -4.0, 1.0, -4.0, -4.0, 1.0]}, {"trial_id": 35089635, "stateRewards": [0.0, -1.0, 1.0, 6.0, -4.0, 4.0, -4.0]}, {"trial_id": 38954377, "stateRewards": [0.0, 1.0, -1.0, -4.0, -1.0, 1.0, -1.0]}, {"trial_id": 68594983, "stateRewards": [0.0, -4.0, 1.0, 4.0, 1.0, 4.0, -1.0]}, {"trial_id": 41093480, "stateRewards": [0.0, 4.0, 1.0, -1.0, -4.0, 1.0, -1.0]}, {"trial_id": 96836874, "stateRewards": [0.0, -4.0, 1.0, -6.0, -1.0, -6.0, 6.0]}, {"trial_id": 43548423, "stateRewards": [0.0, 1.0, -1.0, -1.0, 4.0, 1.0, 1.0]}, {"trial_id": 62902401, "stateRewards": [0.0, -4.0, 6.0, -4.0, -4.0, -1.0, -1.0]}, {"trial_id": 2529190, "stateRewards": [0.0, -1.0, 1.0, 4.0, 4.0, 6.0, 4.0]}, {"trial_id": 67016434, "stateRewards": [0.0, -1.0, 1.0, 1.0, -4.0, 1.0, -6.0]}, {"trial_id": 41159148, "stateRewards": [0.0, 1.0, 4.0, 4.0, 1.0, -1.0, -1.0]}, {"trial_id": 47307187, "stateRewards": [0.0, -4.0, -1.0, -1.0, 4.0, -1.0, 1.0]}, {"trial_id": 91839180, "stateRewards": [0.0, 1.0, -4.0, -1.0, -1.0, -1.0, -4.0]}, {"trial_id": 65687936, "stateRewards": [0.0, -4.0, -1.0, 6.0, -4.0, -6.0, -4.0]}, {"trial_id": 31012951, "stateRewards": [0.0, 4.0, -1.0, 1.0, 6.0, -4.0, 1.0]}, {"trial_id": 51613015, "stateRewards": [0.0, 4.0, 1.0, 6.0, 6.0, 1.0, -6.0]}, {"trial_id": 63674780, "stateRewards": [0.0, -4.0, 1.0, -1.0, 4.0, -1.0, 1.0]}, {"trial_id": 21162636, "stateRewards": [0.0, 1.0, 6.0, 4.0, -1.0, 1.0, -1.0]}, {"trial_id": 68270679, "stateRewards": [0.0, 6.0, 4.0, 1.0, -1.0, 1.0, -6.0]}, {"trial_id": 90117633, "stateRewards": [0.0, -6.0, -4.0, -1.0, 1.0, 4.0, 1.0]}, {"trial_id": 75274317, "stateRewards": [0.0, 1.0, -4.0, -4.0, 6.0, -6.0, 1.0]}, {"trial_id": 6911756, "stateRewards": [0.0, 6.0, -4.0, 1.0, 6.0, 1.0, -4.0]}, {"trial_id": 56178739, "stateRewards": [0.0, -1.0, -4.0, 4.0, 1.0, -6.0, -6.0]}, {"trial_id": 43227546, "stateRewards": [0.0, -1.0, 6.0, 4.0, 1.0, -4.0, -6.0]}, {"trial_id": 6980799, "stateRewards": [0.0, -1.0, -1.0, -1.0, -1.0, -1.0, 1.0]}, {"trial_id": 68014554, "stateRewards": [0.0, 4.0, -1.0, 1.0, -1.0, 4.0, 4.0]}, {"trial_id": 57051786, "stateRewards": [0.0, 1.0, 1.0, 1.0, 1.0, 1.0, 1.0]}, {"trial_id": 34915579, "stateRewards": [0.0, -1.0, 6.0, -1.0, 6.0, 4.0, 1.0]}, {"trial_id": 32192250, "stateRewards": [0.0, -6.0, -1.0, -4.0, -4.0, 1.0, 4.0]}, {"trial_id": 51503255, "stateRewards": [0.0, -6.0, 6.0, 4.0, -6.0, 1.0, 1.0]}, {"trial_id": 33609712, "stateRewards": [0.0, -1.0, 1.0, -1.0, 1.0, 1.0, -1.0]}, {"trial_id": 67954413, "stateRewards": [0.0, 1.0, 1.0, 6.0, -6.0, 4.0, -4.0]}, {"trial_id": 55433529, "stateRewards": [0.0, 4.0, 4.0, 4.0, 1.0, 1.0, 4.0]}, {"trial_id": 63835163, "stateRewards": [0.0, 1.0, -1.0, -1.0, 1.0, 6.0, -1.0]}, {"trial_id": 4589677, "stateRewards": [0.0, -4.0, -4.0, 1.0, 1.0, 4.0, 4.0]}, {"trial_id": 93264802, "stateRewards": [0.0, 1.0, 1.0, 1.0, 4.0, -6.0, 4.0]}, {"trial_id": 57521852, "stateRewards": [0.0, 4.0, -4.0, 1.0, -4.0, 1.0, -4.0]}, {"trial_id": 86036295, "stateRewards": [0.0, -1.0, 4.0, -1.0, 1.0, 1.0, -4.0]}, {"trial_id": 23676212, "stateRewards": [0.0, 4.0, 4.0, 1.0, 4.0, 6.0, 1.0]}, {"trial_id": 32089443, "stateRewards": [0.0, -1.0, -4.0, 1.0, -1.0, 4.0, 1.0]}, {"trial_id": 66732111, "stateRewards": [0.0, -1.0, -6.0, 1.0, -1.0, -1.0, 1.0]}, {"trial_id": 88989246, "stateRewards": [0.0, -4.0, 1.0, 1.0, 1.0, -1.0, -4.0]}, {"trial_id": 87950349, "stateRewards": [0.0, -4.0, 1.0, 6.0, -1.0, 1.0, 4.0]}, {"trial_id": 75692320, "stateRewards": [0.0, -1.0, 1.0, 1.0, 4.0, 1.0, 1.0]}, {"trial_id": 10917531, "stateRewards": [0.0, -4.0, 1.0, 6.0, -6.0, 1.0, 4.0]}, {"trial_id": 4239051, "stateRewards": [0.0, 4.0, 1.0, 1.0, -6.0, -4.0, 4.0]}, {"trial_id": 34604353, "stateRewards": [0.0, 4.0, 1.0, 4.0, -4.0, -6.0, -4.0]}, {"trial_id": 6162737, "stateRewards": [0.0, -1.0, -6.0, -4.0, 4.0, 4.0, 6.0]}, {"trial_id": 30878250, "stateRewards": [0.0, -1.0, 1.0, 1.0, -1.0, -1.0, 6.0]}, {"trial_id": 95634608, "stateRewards": [0.0, -4.0, 4.0, -4.0, 1.0, -1.0, -1.0]}, {"trial_id": 75764383, "stateRewards": [0.0, -1.0, -6.0, -1.0, -1.0, -1.0, 1.0]}, {"trial_id": 84411791, "stateRewards": [0.0, 4.0, 1.0, -1.0, 4.0, -6.0, 4.0]}, {"trial_id": 47478599, "stateRewards": [0.0, 4.0, -4.0, -1.0, 4.0, -4.0, 1.0]}, {"trial_id": 43487620, "stateRewards": [0.0, -6.0, 1.0, -1.0, 1.0, -1.0, -1.0]}, {"trial_id": 64753981, "stateRewards": [0.0, 1.0, -1.0, -1.0, 1.0, -6.0, 1.0]}, {"trial_id": 69671500, "stateRewards": [0.0, 1.0, -1.0, 4.0, -4.0, -4.0, -1.0]}, {"trial_id": 19420996, "stateRewards": [0.0, 1.0, -4.0, 1.0, 1.0, -4.0, 1.0]}, {"trial_id": 99068657, "stateRewards": [0.0, -1.0, 1.0, -1.0, 1.0, -1.0, 1.0]}, {"trial_id": 35405300, "stateRewards": [0.0, -1.0, -1.0, -6.0, -1.0, 1.0, -4.0]}, {"trial_id": 19279439, "stateRewards": [0.0, -1.0, -1.0, -1.0, -4.0, 1.0, -1.0]}, {"trial_id": 37314562, "stateRewards": [0.0, 1.0, 1.0, -1.0, -1.0, 6.0, 1.0]}, {"trial_id": 10634879, "stateRewards": [0.0, 1.0, 4.0, 4.0, -1.0, -4.0, -1.0]}, {"trial_id": 78388929, "stateRewards": [0.0, 4.0, 1.0, -1.0, -1.0, -1.0, -1.0]}, {"trial_id": 91839180, "stateRewards": [0.0, 1.0, -4.0, -1.0, -1.0, -1.0, -4.0]}, {"trial_id": 2805067, "stateRewards": [0.0, -4.0, -1.0, 1.0, -1.0, -4.0, 6.0]}, {"trial_id": 50424610, "stateRewards": [0.0, 1.0, 6.0, -6.0, -4.0, 4.0, 4.0]}, {"trial_id": 65323963, "stateRewards": [0.0, 6.0, -1.0, -1.0, -1.0, -1.0, -1.0]}, {"trial_id": 83316324, "stateRewards": [0.0, -6.0, 6.0, 1.0, -4.0, -1.0, 1.0]}, {"trial_id": 4211917, "stateRewards": [0.0, 6.0, -1.0, -4.0, 1.0, 1.0, 4.0]}, {"trial_id": 16595223, "stateRewards": [0.0, -4.0, 4.0, 6.0, 1.0, -1.0, 1.0]}, {"trial_id": 36732181, "stateRewards": [0.0, -6.0, -1.0, 1.0, -4.0, 6.0, -1.0]}, {"trial_id": 20290433, "stateRewards": [0.0, -1.0, -1.0, -6.0, -1.0, -1.0, -1.0]}, {"trial_id": 5915510, "stateRewards": [0.0, -1.0, -4.0, -4.0, -4.0, 4.0, 4.0]}, {"trial_id": 68523126, "stateRewards": [0.0, 1.0, -1.0, -1.0, 1.0, 4.0, -6.0]}, {"trial_id": 24978183, "stateRewards": [0.0, 4.0, -1.0, -4.0, 1.0, 1.0, -1.0]}, {"trial_id": 93521255, "stateRewards": [0.0, -4.0, 4.0, 1.0, 4.0, 4.0, 1.0]}, {"trial_id": 69661262, "stateRewards": [0.0, -1.0, 1.0, 1.0, -6.0, 1.0, -4.0]}, {"trial_id": 87572633, "stateRewards": [0.0, 4.0, 4.0, 4.0, 1.0, 1.0, -4.0]}, {"trial_id": 85118362, "stateRewards": [0.0, -1.0, 4.0, 1.0, -1.0, 1.0, 4.0]}, {"trial_id": 79729994, "stateRewards": [0.0, 4.0, -4.0, 1.0, 1.0, -1.0, -1.0]}, {"trial_id": 93235960, "stateRewards": [0.0, -4.0, -4.0, 4.0, -6.0, -6.0, 4.0]}, {"trial_id": 6628299, "stateRewards": [0.0, -6.0, 4.0, -1.0, -6.0, 1.0, -6.0]}, {"trial_id": 9549034, "stateRewards": [0.0, -4.0, -1.0, 6.0, 4.0, 4.0, -4.0]}, {"trial_id": 16532688, "stateRewards": [0.0, 4.0, 1.0, 6.0, -1.0, 1.0, -1.0]}, {"trial_id": 69197946, "stateRewards": [0.0, 4.0, 4.0, 6.0, -1.0, 1.0, 4.0]}, {"trial_id": 569559, "stateRewards": [0.0, -4.0, 4.0, -1.0, -1.0, 1.0, -1.0]}, {"trial_id": 99490837, "stateRewards": [0.0, -1.0, -6.0, -1.0, 4.0, -1.0, 1.0]}, {"trial_id": 64007797, "stateRewards": [0.0, -4.0, 1.0, 1.0, 6.0, -1.0, 1.0]}, {"trial_id": 51520099, "stateRewards": [0.0, 4.0, -4.0, -4.0, 4.0, 4.0, 4.0]}, {"trial_id": 42297480, "stateRewards": [0.0, 6.0, 1.0, 1.0, -1.0, -1.0, -4.0]}, {"trial_id": 99612824, "stateRewards": [0.0, -4.0, 6.0, 1.0, -4.0, -6.0, 4.0]}, {"trial_id": 8526071, "stateRewards": [0.0, 6.0, 4.0, 4.0, 1.0, 1.0, -1.0]}, {"trial_id": 4863628, "stateRewards": [0.0, 1.0, -1.0, -4.0, 4.0, -4.0, -1.0]}, {"trial_id": 31903907, "stateRewards": [0.0, 1.0, -1.0, -1.0, -4.0, 4.0, 1.0]}, {"trial_id": 31120452, "stateRewards": [0.0, -1.0, -1.0, -4.0, 4.0, 6.0, -1.0]}, {"trial_id": 14735011, "stateRewards": [0.0, 1.0, -1.0, -4.0, 4.0, 1.0, -1.0]}, {"trial_id": 43273038, "stateRewards": [0.0, 1.0, 1.0, -1.0, -1.0, 1.0, -4.0]}, {"trial_id": 22112537, "stateRewards": [0.0, -4.0, 4.0, 1.0, 1.0, 1.0, -1.0]}, {"trial_id": 15511065, "stateRewards": [0.0, 1.0, -1.0, 4.0, 1.0, -1.0, 4.0]}, {"trial_id": 39472685, "stateRewards": [0.0, 6.0, 1.0, -1.0, -1.0, 4.0, 4.0]}, {"trial_id": 92592354, "stateRewards": [0.0, -4.0, 1.0, -1.0, -1.0, -4.0, -1.0]}, {"trial_id": 37165663, "stateRewards": [0.0, -6.0, 4.0, -1.0, -1.0, -1.0, 6.0]}, {"trial_id": 35031465, "stateRewards": [0.0, -1.0, 4.0, 1.0, -4.0, -1.0, 1.0]}, {"trial_id": 35539905, "stateRewards": [0.0, -1.0, 4.0, -4.0, 1.0, 4.0, 4.0]}, {"trial_id": 94450862, "stateRewards": [0.0, -4.0, 1.0, 1.0, 1.0, 1.0, -4.0]}, {"trial_id": 68447775, "stateRewards": [0.0, -4.0, 4.0, -1.0, 1.0, -1.0, -1.0]}, {"trial_id": 73921546, "stateRewards": [0.0, -1.0, 4.0, 4.0, 6.0, 4.0, -1.0]}, {"trial_id": 97912487, "stateRewards": [0.0, 6.0, 1.0, 1.0, 4.0, -1.0, 1.0]}, {"trial_id": 10434422, "stateRewards": [0.0, 6.0, 4.0, 6.0, 4.0, 4.0, 4.0]}, {"trial_id": 45428993, "stateRewards": [0.0, 1.0, 1.0, -1.0, 1.0, -1.0, -1.0]}, {"trial_id": 73086819, "stateRewards": [0.0, 4.0, -1.0, -4.0, 6.0, 1.0, 4.0]}, {"trial_id": 30717530, "stateRewards": [0.0, 1.0, -6.0, 4.0, -1.0, 6.0, 4.0]}, {"trial_id": 18999871, "stateRewards": [0.0, 6.0, -6.0, 1.0, -1.0, 1.0, 4.0]}, {"trial_id": 4794646, "stateRewards": [0.0, 4.0, 6.0, 1.0, 6.0, 6.0, 1.0]}, {"trial_id": 83847812, "stateRewards": [0.0, 1.0, -1.0, 6.0, 1.0, 4.0, 6.0]}, {"trial_id": 32159257, "stateRewards": [0.0, 6.0, 6.0, -1.0, -1.0, 1.0, -1.0]}, {"trial_id": 89740006, "stateRewards": [0.0, 1.0, -1.0, -1.0, 1.0, 1.0, -4.0]}, {"trial_id": 4191918, "stateRewards": [0.0, -1.0, -6.0, 1.0, 4.0, 4.0, -1.0]}, {"trial_id": 74197384, "stateRewards": [0.0, 6.0, -1.0, 4.0, 4.0, -1.0, 4.0]}, {"trial_id": 8287866, "stateRewards": [0.0, 1.0, -1.0, -4.0, 1.0, 1.0, -4.0]}, {"trial_id": 2767515, "stateRewards": [0.0, 1.0, -1.0, 6.0, -4.0, -4.0, 4.0]}, {"trial_id": 33076857, "stateRewards": [0.0, -1.0, -1.0, 1.0, 1.0, 4.0, -4.0]}, {"trial_id": 86792394, "stateRewards": [0.0, 4.0, 4.0, -6.0, -4.0, 1.0, 6.0]}, {"trial_id": 46425965, "stateRewards": [0.0, 6.0, -1.0, -1.0, 1.0, -4.0, -1.0]}, {"trial_id": 16550377, "stateRewards": [0.0, 1.0, 1.0, 4.0, 1.0, 4.0, -1.0]}, {"trial_id": 96063708, "stateRewards": [0.0, -1.0, -1.0, 6.0, 6.0, 4.0, -1.0]}, {"trial_id": 28032279, "stateRewards": [0.0, -1.0, 4.0, 4.0, 4.0, 1.0, 1.0]}, {"trial_id": 28185085, "stateRewards": [0.0, 1.0, 1.0, -4.0, -4.0, 1.0, 1.0]}, {"trial_id": 79321412, "stateRewards": [0.0, -1.0, 1.0, 1.0, -1.0, 6.0, 6.0]}, {"trial_id": 78725069, "stateRewards": [0.0, -1.0, -1.0, -1.0, 4.0, -1.0, -1.0]}, {"trial_id": 3945024, "stateRewards": [0.0, -1.0, 6.0, 4.0, 4.0, 6.0, -1.0]}, {"trial_id": 40225888, "stateRewards": [0.0, -4.0, -1.0, 1.0, 1.0, 6.0, -6.0]}, {"trial_id": 36952289, "stateRewards": [0.0, -4.0, 1.0, 1.0, 1.0, -1.0, 4.0]}, {"trial_id": 33114047, "stateRewards": [0.0, -1.0, -1.0, 1.0, -1.0, 1.0, 1.0]}, {"trial_id": 34295669, "stateRewards": [0.0, 4.0, -4.0, -1.0, -6.0, 6.0, -1.0]}, {"trial_id": 29926497, "stateRewards": [0.0, 1.0, -6.0, 1.0, 1.0, -1.0, 1.0]}, {"trial_id": 63790642, "stateRewards": [0.0, -1.0, -1.0, 1.0, 1.0, 4.0, -1.0]}, {"trial_id": 16603857, "stateRewards": [0.0, -1.0, -1.0, -4.0, -4.0, 4.0, -6.0]}, {"trial_id": 60344488, "stateRewards": [0.0, -1.0, -1.0, -6.0, -1.0, -4.0, -4.0]}, {"trial_id": 5565558, "stateRewards": [0.0, 6.0, -1.0, -1.0, -1.0, 1.0, -4.0]}, {"trial_id": 59152392, "stateRewards": [0.0, -4.0, 6.0, -1.0, -1.0, -4.0, 1.0]}, {"trial_id": 81411938, "stateRewards": [0.0, 4.0, 1.0, -1.0, -1.0, 4.0, 1.0]}, {"trial_id": 53777610, "stateRewards": [0.0, -4.0, 4.0, 1.0, 1.0, 6.0, -1.0]}, {"trial_id": 87306983, "stateRewards": [0.0, 1.0, -1.0, 1.0, 4.0, 1.0, -1.0]}, {"trial_id": 5736711, "stateRewards": [0.0, 4.0, -1.0, 4.0, -1.0, -4.0, 6.0]}, {"trial_id": 57593013, "stateRewards": [0.0, 1.0, 1.0, -1.0, 4.0, -4.0, 1.0]}, {"trial_id": 12443705, "stateRewards": [0.0, 1.0, 1.0, -6.0, -1.0, 4.0, 1.0]}, {"trial_id": 30627672, "stateRewards": [0.0, -4.0, 4.0, 1.0, 1.0, 4.0, -6.0]}, {"trial_id": 68983341, "stateRewards": [0.0, -1.0, 4.0, 1.0, -1.0, -4.0, -4.0]}, {"trial_id": 35095652, "stateRewards": [0.0, 1.0, 1.0, -4.0, -1.0, -1.0, -1.0]}, {"trial_id": 52347873, "stateRewards": [0.0, 4.0, -4.0, -1.0, -1.0, -1.0, 6.0]}, {"trial_id": 90201264, "stateRewards": [0.0, 1.0, -6.0, 1.0, -1.0, -1.0, -6.0]}, {"trial_id": 47252888, "stateRewards": [0.0, 1.0, -1.0, 1.0, 1.0, 1.0, 1.0]}, {"trial_id": 67217032, "stateRewards": [0.0, 1.0, 6.0, 4.0, -4.0, -1.0, -1.0]}, {"trial_id": 4935807, "stateRewards": [0.0, 1.0, 1.0, 4.0, -1.0, 1.0, -4.0]}, {"trial_id": 90870632, "stateRewards": [0.0, -4.0, -6.0, -1.0, 1.0, -1.0, -1.0]}, {"trial_id": 92241369, "stateRewards": [0.0, -1.0, 1.0, 1.0, 4.0, -1.0, -1.0]}, {"trial_id": 96564169, "stateRewards": [0.0, 1.0, 4.0, -1.0, 4.0, -1.0, -4.0]}, {"trial_id": 15743513, "stateRewards": [0.0, -4.0, -1.0, 6.0, 6.0, -4.0, 1.0]}, {"trial_id": 67338015, "stateRewards": [0.0, 1.0, -1.0, 1.0, 6.0, 6.0, 4.0]}, {"trial_id": 93134313, "stateRewards": [0.0, -4.0, -4.0, -6.0, 1.0, 6.0, -1.0]}, {"trial_id": 94398630, "stateRewards": [0.0, -4.0, -4.0, 4.0, -4.0, -1.0, 4.0]}, {"trial_id": 63662568, "stateRewards": [0.0, 6.0, 4.0, 1.0, -4.0, -4.0, 6.0]}, {"trial_id": 73367994, "stateRewards": [0.0, -1.0, 1.0, 1.0, -6.0, 6.0, -4.0]}, {"trial_id": 28559058, "stateRewards": [0.0, -1.0, 1.0, 1.0, 1.0, -1.0, 4.0]}, {"trial_id": 29368208, "stateRewards": [0.0, -1.0, 1.0, 6.0, -6.0, 4.0, -4.0]}, {"trial_id": 95878317, "stateRewards": [0.0, 6.0, -4.0, 4.0, -6.0, 4.0, -1.0]}, {"trial_id": 14735011, "stateRewards": [0.0, 1.0, -1.0, -4.0, 4.0, 1.0, -1.0]}, {"trial_id": 23048083, "stateRewards": [0.0, -4.0, 1.0, -4.0, -6.0, -1.0, -4.0]}, {"trial_id": 70382083, "stateRewards": [0.0, 4.0, 4.0, -4.0, -1.0, -1.0, -1.0]}, {"trial_id": 96903073, "stateRewards": [0.0, 1.0, 1.0, 4.0, -4.0, 1.0, -1.0]}, {"trial_id": 97975749, "stateRewards": [0.0, -1.0, 4.0, 4.0, -4.0, -6.0, -4.0]}, {"trial_id": 71414456, "stateRewards": [0.0, 1.0, 4.0, 1.0, 4.0, -1.0, -1.0]}, {"trial_id": 68521897, "stateRewards": [0.0, 4.0, 1.0, -1.0, -1.0, 1.0, -1.0]}, {"trial_id": 29089191, "stateRewards": [0.0, 1.0, -6.0, 4.0, -1.0, -1.0, 4.0]}, {"trial_id": 74895860, "stateRewards": [0.0, -4.0, -6.0, 4.0, -1.0, -1.0, -1.0]}, {"trial_id": 92370312, "stateRewards": [0.0, 1.0, -1.0, 6.0, 4.0, 1.0, 1.0]}, {"trial_id": 24774913, "stateRewards": [0.0, -1.0, -4.0, -1.0, -1.0, 4.0, -1.0]}, {"trial_id": 74270918, "stateRewards": [0.0, -6.0, 1.0, 1.0, -1.0, -1.0, -6.0]}, {"trial_id": 35002388, "stateRewards": [0.0, -4.0, -1.0, -4.0, 4.0, -4.0, -1.0]}, {"trial_id": 27727631, "stateRewards": [0.0, -1.0, 6.0, 1.0, -1.0, -1.0, 4.0]}, {"trial_id": 82626795, "stateRewards": [0.0, 6.0, 6.0, -1.0, 6.0, -4.0, 1.0]}, {"trial_id": 73486387, "stateRewards": [0.0, 1.0, 1.0, -4.0, -1.0, 1.0, -6.0]}, {"trial_id": 68452546, "stateRewards": [0.0, -1.0, 1.0, -4.0, 4.0, -1.0, -4.0]}, {"trial_id": 23872639, "stateRewards": [0.0, 1.0, -4.0, 1.0, -4.0, 6.0, -1.0]}, {"trial_id": 85242287, "stateRewards": [0.0, 1.0, -4.0, 4.0, -1.0, -6.0, 1.0]}, {"trial_id": 17602449, "stateRewards": [0.0, -1.0, -1.0, 4.0, -4.0, -6.0, 6.0]}, {"trial_id": 13903249, "stateRewards": [0.0, 6.0, -4.0, 6.0, 1.0, -1.0, -1.0]}, {"trial_id": 5588597, "stateRewards": [0.0, 4.0, 4.0, -1.0, -4.0, 4.0, -1.0]}, {"trial_id": 36482585, "stateRewards": [0.0, -1.0, 4.0, 6.0, -1.0, 1.0, -1.0]}, {"trial_id": 33651364, "stateRewards": [0.0, 6.0, 1.0, 1.0, -1.0, 1.0, -4.0]}, {"trial_id": 53056000, "stateRewards": [0.0, -1.0, 6.0, 1.0, -1.0, 1.0, -1.0]}, {"trial_id": 43877280, "stateRewards": [0.0, 1.0, -4.0, -1.0, -1.0, 1.0, -1.0]}, {"trial_id": 96836159, "stateRewards": [0.0, -1.0, -1.0, 1.0, -6.0, 1.0, -4.0]}, {"trial_id": 1176335, "stateRewards": [0.0, 4.0, 6.0, -1.0, 4.0, -1.0, -4.0]}, {"trial_id": 45137588, "stateRewards": [0.0, -4.0, -4.0, -1.0, -4.0, 4.0, -4.0]}, {"trial_id": 53502861, "stateRewards": [0.0, -1.0, 4.0, 1.0, -6.0, -4.0, -1.0]}, {"trial_id": 29215320, "stateRewards": [0.0, 4.0, -4.0, 1.0, 6.0, -4.0, 1.0]}, {"trial_id": 85815316, "stateRewards": [0.0, -1.0, -4.0, -1.0, -1.0, -1.0, -4.0]}, {"trial_id": 34522986, "stateRewards": [0.0, 1.0, -4.0, 4.0, 4.0, 1.0, -1.0]}, {"trial_id": 18010211, "stateRewards": [0.0, 4.0, 4.0, -4.0, 4.0, -1.0, 1.0]}, {"trial_id": 69948759, "stateRewards": [0.0, 4.0, -1.0, -4.0, -1.0, -1.0, -1.0]}, {"trial_id": 26699435, "stateRewards": [0.0, -1.0, -1.0, -1.0, 1.0, -1.0, 4.0]}, {"trial_id": 89359388, "stateRewards": [0.0, 1.0, -1.0, -1.0, -6.0, -1.0, 4.0]}, {"trial_id": 81353117, "stateRewards": [0.0, 1.0, -4.0, -4.0, 4.0, -4.0, -1.0]}, {"trial_id": 44874108, "stateRewards": [0.0, 1.0, -4.0, -6.0, -4.0, -4.0, 1.0]}, {"trial_id": 94521585, "stateRewards": [0.0, -1.0, -1.0, 1.0, 4.0, 4.0, -4.0]}, {"trial_id": 29199486, "stateRewards": [0.0, 1.0, 1.0, 4.0, -4.0, 1.0, -4.0]}, {"trial_id": 12356209, "stateRewards": [0.0, 1.0, -6.0, 1.0, 4.0, -1.0, 4.0]}, {"trial_id": 97751921, "stateRewards": [0.0, 6.0, 1.0, -4.0, -1.0, -1.0, -1.0]}, {"trial_id": 12366127, "stateRewards": [0.0, -1.0, 1.0, 4.0, 1.0, 4.0, -6.0]}, {"trial_id": 18029266, "stateRewards": [0.0, 6.0, 1.0, 1.0, -1.0, -1.0, -1.0]}, {"trial_id": 78354906, "stateRewards": [0.0, 1.0, -4.0, 1.0, 1.0, 6.0, -1.0]}, {"trial_id": 97440098, "stateRewards": [0.0, -1.0, 6.0, 6.0, -4.0, -1.0, -1.0]}, {"trial_id": 26467204, "stateRewards": [0.0, 1.0, 1.0, 1.0, -1.0, -1.0, -1.0]}, {"trial_id": 77460207, "stateRewards": [0.0, 4.0, 1.0, 1.0, -1.0, 1.0, -4.0]}, {"trial_id": 80213387, "stateRewards": [0.0, -1.0, -6.0, 4.0, -6.0, 4.0, -4.0]}, {"trial_id": 24961105, "stateRewards": [0.0, -1.0, 1.0, -1.0, 1.0, -1.0, 4.0]}, {"trial_id": 74064383, "stateRewards": [0.0, -1.0, -4.0, 6.0, 6.0, 4.0, -4.0]}, {"trial_id": 33329105, "stateRewards": [0.0, 4.0, -6.0, 1.0, 1.0, 4.0, 4.0]}, {"trial_id": 61534327, "stateRewards": [0.0, 4.0, -1.0, -1.0, -1.0, 1.0, -1.0]}, {"trial_id": 87123495, "stateRewards": [0.0, 1.0, -1.0, 1.0, -6.0, 1.0, 4.0]}, {"trial_id": 64264972, "stateRewards": [0.0, 1.0, -1.0, -4.0, -4.0, 4.0, 6.0]}, {"trial_id": 37407767, "stateRewards": [0.0, 1.0, -4.0, -4.0, -1.0, 1.0, 1.0]}, {"trial_id": 40212083, "stateRewards": [0.0, 6.0, -1.0, -1.0, -4.0, -1.0, 1.0]}, {"trial_id": 73340016, "stateRewards": [0.0, -4.0, -4.0, 1.0, 6.0, -4.0, 1.0]}, {"trial_id": 84498723, "stateRewards": [0.0, -1.0, 1.0, 1.0, -1.0, 1.0, 6.0]}, {"trial_id": 12107349, "stateRewards": [0.0, -4.0, 1.0, 1.0, -4.0, -4.0, -1.0]}, {"trial_id": 63279576, "stateRewards": [0.0, -4.0, 1.0, -4.0, 1.0, -1.0, 1.0]}, {"trial_id": 56363855, "stateRewards": [0.0, -1.0, 4.0, 1.0, 6.0, -1.0, 6.0]}, {"trial_id": 75015969, "stateRewards": [0.0, 4.0, 1.0, -1.0, -1.0, -1.0, -6.0]}, {"trial_id": 60576748, "stateRewards": [0.0, 1.0, 1.0, 1.0, 1.0, 6.0, 1.0]}, {"trial_id": 4848344, "stateRewards": [0.0, 4.0, -4.0, 4.0, -4.0, -6.0, 4.0]}, {"trial_id": 37444547, "stateRewards": [0.0, -4.0, -1.0, -1.0, 6.0, -1.0, 1.0]}, {"trial_id": 70338333, "stateRewards": [0.0, -1.0, -1.0, -4.0, 4.0, 1.0, 4.0]}, {"trial_id": 16384199, "stateRewards": [0.0, -1.0, 1.0, -1.0, -4.0, 1.0, -1.0]}, {"trial_id": 22055664, "stateRewards": [0.0, 1.0, -4.0, -1.0, -1.0, -6.0, 4.0]}, {"trial_id": 9598431, "stateRewards": [0.0, 4.0, -6.0, -4.0, -4.0, 1.0, 1.0]}, {"trial_id": 88407996, "stateRewards": [0.0, -1.0, 4.0, -4.0, 6.0, 1.0, 4.0]}, {"trial_id": 75894290, "stateRewards": [0.0, -1.0, -1.0, 4.0, 1.0, 4.0, 1.0]}, {"trial_id": 2411356, "stateRewards": [0.0, 4.0, 1.0, -4.0, 1.0, 4.0, 1.0]}, {"trial_id": 9912975, "stateRewards": [0.0, 1.0, -1.0, 1.0, -4.0, -6.0, -1.0]}, {"trial_id": 10778662, "stateRewards": [0.0, -1.0, -4.0, -1.0, -4.0, -1.0, -4.0]}, {"trial_id": 45740157, "stateRewards": [0.0, 1.0, 6.0, 1.0, -4.0, -6.0, -4.0]}, {"trial_id": 70901799, "stateRewards": [0.0, 1.0, 1.0, -4.0, 1.0, -1.0, 1.0]}, {"trial_id": 33552583, "stateRewards": [0.0, 1.0, 1.0, -1.0, 6.0, 4.0, -1.0]}, {"trial_id": 42712898, "stateRewards": [0.0, -4.0, 1.0, 1.0, 4.0, 1.0, -1.0]}, {"trial_id": 87348067, "stateRewards": [0.0, 6.0, -1.0, 1.0, -4.0, 4.0, -1.0]}, {"trial_id": 46590399, "stateRewards": [0.0, 4.0, 1.0, -4.0, -1.0, -1.0, -6.0]}, {"trial_id": 89303119, "stateRewards": [0.0, 1.0, 4.0, -4.0, -1.0, 4.0, -4.0]}, {"trial_id": 77145576, "stateRewards": [0.0, 1.0, -6.0, -1.0, 6.0, -1.0, 1.0]}, {"trial_id": 17240623, "stateRewards": [0.0, -1.0, 1.0, -1.0, -4.0, 1.0, 1.0]}, {"trial_id": 78206330, "stateRewards": [0.0, -1.0, -4.0, -4.0, 1.0, -1.0, -1.0]}, {"trial_id": 18929292, "stateRewards": [0.0, -1.0, 1.0, -1.0, 4.0, -1.0, -4.0]}, {"trial_id": 60344486, "stateRewards": [0.0, -1.0, 1.0, 1.0, -6.0, 6.0, 4.0]}, {"trial_id": 11550759, "stateRewards": [0.0, -4.0, 1.0, 1.0, 1.0, 4.0, -1.0]}, {"trial_id": 22055664, "stateRewards": [0.0, 1.0, -4.0, -1.0, -1.0, -6.0, 4.0]}, {"trial_id": 15305658, "stateRewards": [0.0, 1.0, 1.0, -4.0, -1.0, -4.0, -1.0]}, {"trial_id": 88641519, "stateRewards": [0.0, 1.0, -4.0, -4.0, -4.0, 6.0, 1.0]}, {"trial_id": 18203776, "stateRewards": [0.0, -4.0, 6.0, -4.0, 1.0, 1.0, -6.0]}, {"trial_id": 45969275, "stateRewards": [0.0, 4.0, 4.0, -1.0, -1.0, 1.0, 1.0]}, {"trial_id": 90117633, "stateRewards": [0.0, -6.0, -4.0, -1.0, 1.0, 4.0, 1.0]}, {"trial_id": 44349508, "stateRewards": [0.0, -1.0, -4.0, -4.0, 6.0, -1.0, -1.0]}, {"trial_id": 61151228, "stateRewards": [0.0, -6.0, -4.0, 1.0, 4.0, -4.0, 1.0]}, {"trial_id": 38249877, "stateRewards": [0.0, 4.0, -1.0, 6.0, -1.0, -1.0, 1.0]}, {"trial_id": 27086437, "stateRewards": [0.0, -4.0, -4.0, 1.0, 1.0, 1.0, -1.0]}, {"trial_id": 76183099, "stateRewards": [0.0, 4.0, 1.0, 1.0, 6.0, 6.0, 4.0]}, {"trial_id": 60645598, "stateRewards": [0.0, -6.0, -1.0, 1.0, 4.0, 1.0, 4.0]}, {"trial_id": 10404325, "stateRewards": [0.0, -6.0, 1.0, -4.0, 4.0, -1.0, -1.0]}, {"trial_id": 78807675, "stateRewards": [0.0, -4.0, -1.0, -1.0, -4.0, 1.0, -4.0]}, {"trial_id": 52953294, "stateRewards": [0.0, 1.0, -4.0, 6.0, -1.0, 4.0, -4.0]}, {"trial_id": 28483126, "stateRewards": [0.0, -1.0, 1.0, 1.0, -4.0, 1.0, 1.0]}, {"trial_id": 78748384, "stateRewards": [0.0, -4.0, 4.0, -1.0, 4.0, 4.0, -1.0]}, {"trial_id": 41871856, "stateRewards": [0.0, -1.0, -4.0, -1.0, -1.0, -1.0, 1.0]}, {"trial_id": 45745453, "stateRewards": [0.0, -1.0, 4.0, 4.0, -4.0, 1.0, 4.0]}, {"trial_id": 85507495, "stateRewards": [0.0, 1.0, -1.0, -1.0, -1.0, 1.0, -4.0]}, {"trial_id": 12079546, "stateRewards": [0.0, 1.0, -1.0, 1.0, -1.0, 4.0, -1.0]}, {"trial_id": 4072993, "stateRewards": [0.0, -6.0, 4.0, 4.0, 1.0, 4.0, -1.0]}, {"trial_id": 25960241, "stateRewards": [0.0, -1.0, 4.0, 1.0, -1.0, 4.0, -1.0]}, {"trial_id": 35225148, "stateRewards": [0.0, 1.0, -4.0, -4.0, -1.0, -1.0, -1.0]}, {"trial_id": 64753981, "stateRewards": [0.0, 1.0, -1.0, -1.0, 1.0, -6.0, 1.0]}, {"trial_id": 55624678, "stateRewards": [0.0, -1.0, 1.0, 4.0, -4.0, 1.0, 1.0]}, {"trial_id": 99967342, "stateRewards": [0.0, 1.0, 1.0, -1.0, -1.0, -1.0, 4.0]}, {"trial_id": 99945700, "stateRewards": [0.0, -1.0, -1.0, -1.0, -4.0, 1.0, 1.0]}, {"trial_id": 34367115, "stateRewards": [0.0, -4.0, -4.0, 4.0, 1.0, 1.0, -1.0]}, {"trial_id": 73112855, "stateRewards": [0.0, 1.0, -1.0, -1.0, 1.0, 4.0, -1.0]}, {"trial_id": 40980993, "stateRewards": [0.0, 1.0, -6.0, -1.0, -1.0, 1.0, 1.0]}, {"trial_id": 27591641, "stateRewards": [0.0, 1.0, -4.0, -4.0, -1.0, 4.0, -1.0]}, {"trial_id": 95354185, "stateRewards": [0.0, 1.0, -1.0, -4.0, 6.0, -1.0, 1.0]}, {"trial_id": 66341284, "stateRewards": [0.0, -4.0, -1.0, 6.0, -1.0, -1.0, 6.0]}, {"trial_id": 39050097, "stateRewards": [0.0, 6.0, 1.0, 4.0, 1.0, 4.0, -1.0]}, {"trial_id": 65673528, "stateRewards": [0.0, -1.0, 4.0, 1.0, 1.0, -1.0, -4.0]}, {"trial_id": 37787512, "stateRewards": [0.0, -1.0, 1.0, -1.0, -4.0, 1.0, 4.0]}, {"trial_id": 75805268, "stateRewards": [0.0, 6.0, -1.0, 1.0, 6.0, 1.0, -1.0]}, {"trial_id": 39761290, "stateRewards": [0.0, -4.0, 1.0, 1.0, -1.0, -6.0, -4.0]}, {"trial_id": 66599304, "stateRewards": [0.0, -6.0, 4.0, 1.0, -4.0, 1.0, 4.0]}, {"trial_id": 1023452, "stateRewards": [0.0, 4.0, -1.0, -4.0, 1.0, -1.0, 1.0]}, {"trial_id": 33142288, "stateRewards": [0.0, -4.0, -4.0, -1.0, 1.0, 1.0, 4.0]}, {"trial_id": 83128488, "stateRewards": [0.0, 4.0, 1.0, -1.0, -1.0, 1.0, 4.0]}, {"trial_id": 94252059, "stateRewards": [0.0, -1.0, -1.0, 6.0, -1.0, -1.0, 1.0]}, {"trial_id": 21682679, "stateRewards": [0.0, 4.0, 4.0, 1.0, 4.0, 1.0, 4.0]}, {"trial_id": 96344136, "stateRewards": [0.0, -1.0, 4.0, -4.0, -1.0, 1.0, -1.0]}, {"trial_id": 28523848, "stateRewards": [0.0, -4.0, -1.0, 4.0, -1.0, -1.0, 1.0]}, {"trial_id": 89398631, "stateRewards": [0.0, -4.0, 1.0, -4.0, -4.0, -1.0, -1.0]}, {"trial_id": 84483654, "stateRewards": [0.0, 1.0, 6.0, -1.0, 1.0, -4.0, -4.0]}, {"trial_id": 47147329, "stateRewards": [0.0, 6.0, -1.0, -1.0, -4.0, 6.0, -6.0]}, {"trial_id": 70947003, "stateRewards": [0.0, 1.0, 1.0, -6.0, 4.0, -1.0, 1.0]}, {"trial_id": 32402931, "stateRewards": [0.0, -1.0, 4.0, -4.0, 1.0, 6.0, -1.0]}, {"trial_id": 28552541, "stateRewards": [0.0, 6.0, 1.0, -1.0, -1.0, 1.0, -4.0]}, {"trial_id": 34487051, "stateRewards": [0.0, -1.0, -1.0, -6.0, -1.0, -4.0, -1.0]}, {"trial_id": 48642143, "stateRewards": [0.0, -1.0, 1.0, 6.0, 4.0, 1.0, -1.0]}, {"trial_id": 96309692, "stateRewards": [0.0, -1.0, 4.0, 1.0, 1.0, -1.0, 1.0]}, {"trial_id": 74339019, "stateRewards": [0.0, 4.0, 1.0, 4.0, 4.0, -1.0, 6.0]}, {"trial_id": 49958718, "stateRewards": [0.0, -1.0, -1.0, 1.0, 1.0, 6.0, -6.0]}, {"trial_id": 60854143, "stateRewards": [0.0, 4.0, 1.0, -1.0, 1.0, 1.0, -1.0]}, {"trial_id": 43020476, "stateRewards": [0.0, -1.0, -1.0, 4.0, 1.0, 1.0, -1.0]}, {"trial_id": 24879976, "stateRewards": [0.0, 1.0, 4.0, -4.0, -6.0, -1.0, -1.0]}, {"trial_id": 82122955, "stateRewards": [0.0, 1.0, -1.0, -4.0, -1.0, -4.0, -6.0]}, {"trial_id": 18087624, "stateRewards": [0.0, 1.0, -1.0, 1.0, -1.0, 1.0, 6.0]}, {"trial_id": 53211402, "stateRewards": [0.0, -1.0, -1.0, 1.0, -4.0, 4.0, -1.0]}, {"trial_id": 79605153, "stateRewards": [0.0, -1.0, 1.0, 4.0, 6.0, 4.0, 1.0]}, {"trial_id": 75875771, "stateRewards": [0.0, 1.0, -1.0, -4.0, 1.0, -1.0, 1.0]}, {"trial_id": 78582333, "stateRewards": [0.0, 1.0, -1.0, 1.0, 6.0, -1.0, 1.0]}, {"trial_id": 65501199, "stateRewards": [0.0, -1.0, 1.0, -4.0, -1.0, -1.0, -1.0]}, {"trial_id": 95242397, "stateRewards": [0.0, -4.0, 4.0, 4.0, 1.0, -1.0, -1.0]}, {"trial_id": 25225389, "stateRewards": [0.0, -1.0, 4.0, 1.0, 1.0, -1.0, 4.0]}, {"trial_id": 26005892, "stateRewards": [0.0, 1.0, -1.0, -1.0, -4.0, 6.0, 4.0]}, {"trial_id": 42712898, "stateRewards": [0.0, -4.0, 1.0, 1.0, 4.0, 1.0, -1.0]}, {"trial_id": 87230330, "stateRewards": [0.0, 4.0, 1.0, 4.0, 1.0, -1.0, -1.0]}, {"trial_id": 67099217, "stateRewards": [0.0, 1.0, -1.0, 1.0, 1.0, 1.0, -4.0]}, {"trial_id": 82234481, "stateRewards": [0.0, 1.0, 4.0, -4.0, -1.0, 1.0, 4.0]}, {"trial_id": 43897144, "stateRewards": [0.0, -1.0, 1.0, -1.0, 4.0, 1.0, 1.0]}, {"trial_id": 53220439, "stateRewards": [0.0, 1.0, -1.0, -1.0, -1.0, 6.0, -4.0]}, {"trial_id": 88810477, "stateRewards": [0.0, 1.0, -1.0, 1.0, -4.0, -1.0, -1.0]}, {"trial_id": 43119195, "stateRewards": [0.0, -4.0, -4.0, 6.0, -4.0, 1.0, 1.0]}, {"trial_id": 79012349, "stateRewards": [0.0, -1.0, 1.0, 1.0, 4.0, 1.0, -1.0]}, {"trial_id": 93838696, "stateRewards": [0.0, 1.0, -4.0, -1.0, -4.0, -4.0, 1.0]}, {"trial_id": 85894183, "stateRewards": [0.0, -1.0, 4.0, 1.0, -1.0, 6.0, 4.0]}, {"trial_id": 22977057, "stateRewards": [0.0, 6.0, 1.0, 4.0, -1.0, 1.0, -4.0]}, {"trial_id": 94298917, "stateRewards": [0.0, 1.0, 4.0, 1.0, -6.0, 1.0, 4.0]}, {"trial_id": 97908132, "stateRewards": [0.0, -4.0, 1.0, -4.0, -6.0, 6.0, 1.0]}, {"trial_id": 58880028, "stateRewards": [0.0, -4.0, -1.0, -1.0, 1.0, 1.0, -4.0]}, {"trial_id": 79025025, "stateRewards": [0.0, -1.0, 1.0, -1.0, 1.0, 1.0, -4.0]}, {"trial_id": 56984321, "stateRewards": [0.0, 4.0, -4.0, -1.0, -4.0, 4.0, 1.0]}, {"trial_id": 40269238, "stateRewards": [0.0, -4.0, -1.0, -1.0, 6.0, -4.0, -1.0]}, {"trial_id": 85556391, "stateRewards": [0.0, 4.0, 1.0, -4.0, 1.0, 1.0, -4.0]}, {"trial_id": 93803068, "stateRewards": [0.0, -4.0, 4.0, -1.0, 4.0, 1.0, -6.0]}, {"trial_id": 44536626, "stateRewards": [0.0, -4.0, 4.0, 1.0, -1.0, 4.0, -1.0]}, {"trial_id": 94539706, "stateRewards": [0.0, 4.0, 1.0, -1.0, 1.0, -4.0, 1.0]}, {"trial_id": 15349641, "stateRewards": [0.0, -1.0, 1.0, -1.0, -1.0, 1.0, 1.0]}, {"trial_id": 9186177, "stateRewards": [0.0, 1.0, 4.0, -4.0, -1.0, -4.0, -1.0]}, {"trial_id": 35427117, "stateRewards": [0.0, 1.0, -1.0, 4.0, 1.0, 1.0, -1.0]}, {"trial_id": 73378546, "stateRewards": [0.0, 1.0, 1.0, 1.0, 1.0, -4.0, 1.0]}, {"trial_id": 59069774, "stateRewards": [0.0, -4.0, -1.0, -1.0, -1.0, 1.0, -1.0]}, {"trial_id": 29036198, "stateRewards": [0.0, 4.0, 1.0, -1.0, -1.0, 4.0, -1.0]}, {"trial_id": 36628061, "stateRewards": [0.0, -1.0, -1.0, 1.0, -4.0, -1.0, -4.0]}, {"trial_id": 91430185, "stateRewards": [0.0, -4.0, -1.0, 4.0, 1.0, 4.0, -1.0]}, {"trial_id": 92230115, "stateRewards": [0.0, -1.0, 1.0, -1.0, -4.0, -1.0, -4.0]}, {"trial_id": 6635114, "stateRewards": [0.0, -1.0, 6.0, -4.0, -1.0, 1.0, -1.0]}, {"trial_id": 86050486, "stateRewards": [0.0, 1.0, -4.0, 4.0, 4.0, -4.0, -1.0]}, {"trial_id": 26794443, "stateRewards": [0.0, -4.0, -1.0, -4.0, 1.0, -6.0, 4.0]}, {"trial_id": 28786742, "stateRewards": [0.0, 4.0, 1.0, -4.0, 1.0, -4.0, 1.0]}, {"trial_id": 36628061, "stateRewards": [0.0, -1.0, -1.0, 1.0, -4.0, -1.0, -4.0]}, {"trial_id": 21621811, "stateRewards": [0.0, -1.0, 4.0, 4.0, -6.0, 4.0, -1.0]}, {"trial_id": 12434097, "stateRewards": [0.0, 4.0, 4.0, -4.0, 4.0, -1.0, -4.0]}, {"trial_id": 95144987, "stateRewards": [0.0, -1.0, -4.0, 6.0, 1.0, 1.0, 1.0]}, {"trial_id": 69643080, "stateRewards": [0.0, 1.0, 4.0, -1.0, 1.0, 1.0, -1.0]}, {"trial_id": 50879269, "stateRewards": [0.0, 6.0, -4.0, -1.0, -1.0, 1.0, -1.0]}, {"trial_id": 8142497, "stateRewards": [0.0, -1.0, 4.0, 1.0, -6.0, -1.0, -4.0]}, {"trial_id": 86923449, "stateRewards": [0.0, 1.0, -4.0, 1.0, -1.0, 4.0, 1.0]}, {"trial_id": 55059613, "stateRewards": [0.0, 4.0, -1.0, -4.0, 6.0, 4.0, 4.0]}, {"trial_id": 63853820, "stateRewards": [0.0, 1.0, -1.0, 6.0, -1.0, -4.0, -4.0]}, {"trial_id": 5375612, "stateRewards": [0.0, 1.0, -1.0, -4.0, 1.0, -1.0, -1.0]}, {"trial_id": 40227717, "stateRewards": [0.0, -1.0, -1.0, -1.0, 1.0, 1.0, -1.0]}, {"trial_id": 45938877, "stateRewards": [0.0, -4.0, 4.0, -1.0, 4.0, -6.0, -4.0]}, {"trial_id": 85083117, "stateRewards": [0.0, -4.0, -4.0, -1.0, -1.0, 1.0, -1.0]}, {"trial_id": 7913616, "stateRewards": [0.0, 1.0, 4.0, 4.0, 1.0, -4.0, 4.0]}, {"trial_id": 14463957, "stateRewards": [0.0, -1.0, 1.0, 1.0, 1.0, -1.0, 1.0]}, {"trial_id": 68688086, "stateRewards": [0.0, 1.0, -4.0, 1.0, 1.0, -1.0, -1.0]}, {"trial_id": 58925132, "stateRewards": [0.0, 1.0, 4.0, 1.0, 4.0, -1.0, 4.0]}, {"trial_id": 34192444, "stateRewards": [0.0, -4.0, -4.0, 1.0, 1.0, -1.0, 1.0]}, {"trial_id": 80734333, "stateRewards": [0.0, 1.0, -4.0, 1.0, 1.0, -1.0, 6.0]}, {"trial_id": 67099217, "stateRewards": [0.0, 1.0, -1.0, 1.0, 1.0, 1.0, -4.0]}, {"trial_id": 95634608, "stateRewards": [0.0, -4.0, 4.0, -4.0, 1.0, -1.0, -1.0]}, {"trial_id": 93412415, "stateRewards": [0.0, -1.0, -1.0, -4.0, -4.0, -1.0, -6.0]}, {"trial_id": 4626178, "stateRewards": [0.0, 1.0, 1.0, -1.0, -1.0, -1.0, 1.0]}, {"trial_id": 94757135, "stateRewards": [0.0, 1.0, -1.0, -4.0, -1.0, 1.0, 1.0]}, {"trial_id": 55319955, "stateRewards": [0.0, 4.0, -1.0, -1.0, -1.0, 4.0, 1.0]}, {"trial_id": 36249604, "stateRewards": [0.0, 1.0, -1.0, -1.0, -1.0, -1.0, 4.0]}, {"trial_id": 85871571, "stateRewards": [0.0, -4.0, 4.0, -1.0, -4.0, 4.0, 1.0]}, {"trial_id": 34816943, "stateRewards": [0.0, -1.0, -6.0, 6.0, 4.0, -1.0, -1.0]}, {"trial_id": 63684923, "stateRewards": [0.0, -1.0, 1.0, 4.0, 1.0, 4.0, -1.0]}, {"trial_id": 79262692, "stateRewards": [0.0, 4.0, -6.0, -1.0, -1.0, 6.0, -1.0]}, {"trial_id": 90168846, "stateRewards": [0.0, 4.0, -1.0, 1.0, 1.0, -1.0, -4.0]}, {"trial_id": 52484399, "stateRewards": [0.0, 4.0, 4.0, -1.0, 1.0, -1.0, 1.0]}, {"trial_id": 57051786, "stateRewards": [0.0, 1.0, 1.0, 1.0, 1.0, 1.0, 1.0]}, {"trial_id": 48659276, "stateRewards": [0.0, 1.0, 1.0, -1.0, -1.0, -1.0, -4.0]}, {"trial_id": 56312170, "stateRewards": [0.0, 1.0, -4.0, 1.0, 6.0, -1.0, 1.0]}, {"trial_id": 70372666, "stateRewards": [0.0, 1.0, -1.0, 4.0, -1.0, -6.0, 6.0]}, {"trial_id": 82908113, "stateRewards": [0.0, -1.0, -1.0, -4.0, 4.0, 1.0, -4.0]}, {"trial_id": 54973932, "stateRewards": [0.0, 1.0, -4.0, 4.0, 1.0, -4.0, -1.0]}, {"trial_id": 79069543, "stateRewards": [0.0, -1.0, -1.0, -1.0, -1.0, 6.0, -4.0]}, {"trial_id": 49604830, "stateRewards": [0.0, -1.0, -6.0, 1.0, 4.0, -1.0, -4.0]}, {"trial_id": 73701525, "stateRewards": [0.0, 1.0, 1.0, -4.0, -4.0, 4.0, -1.0]}, {"trial_id": 91663425, "stateRewards": [0.0, 1.0, -6.0, 4.0, 1.0, 1.0, -1.0]}, {"trial_id": 85488314, "stateRewards": [0.0, -4.0, 6.0, 1.0, -1.0, -1.0, -1.0]}, {"trial_id": 35144284, "stateRewards": [0.0, -1.0, -4.0, 1.0, -1.0, -1.0, 6.0]}, {"trial_id": 94577699, "stateRewards": [0.0, 1.0, -1.0, 1.0, -1.0, 4.0, 4.0]}, {"trial_id": 6267325, "stateRewards": [0.0, 1.0, -4.0, -1.0, -1.0, 1.0, 4.0]}, {"trial_id": 46709830, "stateRewards": [0.0, -6.0, -6.0, -4.0, 4.0, 1.0, 1.0]}, {"trial_id": 10345257, "stateRewards": [0.0, 1.0, -1.0, 6.0, -1.0, -1.0, -1.0]}, {"trial_id": 62700377, "stateRewards": [0.0, -4.0, 6.0, 4.0, -6.0, -4.0, -1.0]}, {"trial_id": 17914933, "stateRewards": [0.0, 1.0, 1.0, -6.0, 4.0, 1.0, 1.0]}, {"trial_id": 7751460, "stateRewards": [0.0, 4.0, 1.0, 4.0, -1.0, -1.0, 1.0]}, {"trial_id": 78501470, "stateRewards": [0.0, 1.0, 4.0, -1.0, -4.0, 1.0, 1.0]}, {"trial_id": 57078203, "stateRewards": [0.0, -1.0, 4.0, -1.0, 1.0, 1.0, -1.0]}, {"trial_id": 82867923, "stateRewards": [0.0, 4.0, -1.0, -1.0, 4.0, -6.0, 1.0]}, {"trial_id": 46806248, "stateRewards": [0.0, 1.0, 1.0, 4.0, -1.0, 1.0, 1.0]}, {"trial_id": 25250308, "stateRewards": [0.0, -1.0, -1.0, -1.0, -1.0, 4.0, 1.0]}, {"trial_id": 99817257, "stateRewards": [0.0, -1.0, 1.0, 6.0, -1.0, -1.0, -4.0]}, {"trial_id": 66355125, "stateRewards": [0.0, 4.0, 6.0, -1.0, -4.0, 4.0, 1.0]}, {"trial_id": 36356048, "stateRewards": [0.0, -4.0, -1.0, -4.0, -4.0, -1.0, 4.0]}, {"trial_id": 62879423, "stateRewards": [0.0, 4.0, -6.0, 6.0, 1.0, 6.0, -1.0]}, {"trial_id": 68740190, "stateRewards": [0.0, 1.0, 4.0, 4.0, 1.0, -1.0, -4.0]}, {"trial_id": 80817887, "stateRewards": [0.0, -1.0, 1.0, 1.0, 1.0, 1.0, -1.0]}, {"trial_id": 45999098, "stateRewards": [0.0, -4.0, -1.0, 4.0, -1.0, -4.0, -1.0]}, {"trial_id": 27478683, "stateRewards": [0.0, 1.0, 1.0, 4.0, -1.0, -1.0, 4.0]}, {"trial_id": 64948884, "stateRewards": [0.0, -4.0, -1.0, -4.0, 1.0, 4.0, 4.0]}, {"trial_id": 51697648, "stateRewards": [0.0, -1.0, -1.0, 4.0, 4.0, 4.0, -4.0]}, {"trial_id": 76265091, "stateRewards": [0.0, -1.0, 6.0, -1.0, 1.0, -4.0, 1.0]}, {"trial_id": 40980955, "stateRewards": [0.0, -4.0, -4.0, -4.0, 1.0, 4.0, 4.0]}, {"trial_id": 11933462, "stateRewards": [0.0, 1.0, 1.0, 1.0, 4.0, 1.0, 1.0]}, {"trial_id": 36804814, "stateRewards": [0.0, -1.0, 6.0, 1.0, -1.0, 4.0, 1.0]}, {"trial_id": 2214271, "stateRewards": [0.0, 1.0, 1.0, 4.0, 4.0, 1.0, 1.0]}, {"trial_id": 35375587, "stateRewards": [0.0, -6.0, -4.0, 1.0, -1.0, -4.0, -6.0]}, {"trial_id": 93581647, "stateRewards": [0.0, -1.0, 1.0, 1.0, 4.0, -4.0, -6.0]}, {"trial_id": 57803199, "stateRewards": [0.0, -1.0, -1.0, -4.0, 4.0, -1.0, 4.0]}, {"trial_id": 68844506, "stateRewards": [0.0, -4.0, 4.0, 4.0, -1.0, -1.0, -4.0]}, {"trial_id": 34161241, "stateRewards": [0.0, 1.0, 1.0, 1.0, -4.0, 1.0, 1.0]}, {"trial_id": 34796304, "stateRewards": [0.0, 1.0, 1.0, -4.0, 4.0, -1.0, 4.0]}, {"trial_id": 98875453, "stateRewards": [0.0, -4.0, -1.0, 4.0, 1.0, -4.0, 4.0]}, {"trial_id": 81086137, "stateRewards": [0.0, 4.0, 4.0, 1.0, 6.0, 4.0, -1.0]}, {"trial_id": 23728603, "stateRewards": [0.0, -4.0, -1.0, 1.0, 1.0, -4.0, 4.0]}, {"trial_id": 89097469, "stateRewards": [0.0, 1.0, -4.0, 1.0, 4.0, -1.0, -1.0]}, {"trial_id": 57177852, "stateRewards": [0.0, 1.0, 1.0, 1.0, -1.0, 1.0, -1.0]}, {"trial_id": 55712979, "stateRewards": [0.0, -4.0, -1.0, 1.0, -6.0, 6.0, 1.0]}, {"trial_id": 65507996, "stateRewards": [0.0, -6.0, -4.0, -6.0, -4.0, 4.0, 4.0]}, {"trial_id": 42494412, "stateRewards": [0.0, 1.0, -1.0, -1.0, -1.0, -4.0, 1.0]}, {"trial_id": 43450826, "stateRewards": [0.0, 4.0, -6.0, 1.0, -1.0, -1.0, 1.0]}, {"trial_id": 23507750, "stateRewards": [0.0, 1.0, 4.0, 1.0, -1.0, -4.0, 6.0]}, {"trial_id": 94929352, "stateRewards": [0.0, 1.0, -4.0, -1.0, -6.0, -6.0, -1.0]}, {"trial_id": 4187890, "stateRewards": [0.0, -4.0, -6.0, -1.0, -1.0, -1.0, -4.0]}, {"trial_id": 90752091, "stateRewards": [0.0, -1.0, 6.0, 6.0, -1.0, 4.0, -1.0]}, {"trial_id": 72000027, "stateRewards": [0.0, -1.0, -4.0, -1.0, 1.0, -6.0, 1.0]}, {"trial_id": 43548423, "stateRewards": [0.0, 1.0, -1.0, -1.0, 4.0, 1.0, 1.0]}, {"trial_id": 27586254, "stateRewards": [0.0, 4.0, 4.0, -1.0, 1.0, 1.0, -1.0]}, {"trial_id": 89440748, "stateRewards": [0.0, -4.0, -1.0, -1.0, 4.0, -1.0, 6.0]}, {"trial_id": 41857598, "stateRewards": [0.0, -4.0, -1.0, 1.0, 1.0, 4.0, -1.0]}, {"trial_id": 20429861, "stateRewards": [0.0, 1.0, -1.0, 1.0, 1.0, 4.0, -4.0]}, {"trial_id": 67077953, "stateRewards": [0.0, 1.0, -6.0, 4.0, 4.0, -4.0, -4.0]}, {"trial_id": 13939737, "stateRewards": [0.0, -6.0, -4.0, 1.0, 1.0, 4.0, -1.0]}, {"trial_id": 99013137, "stateRewards": [0.0, -1.0, -4.0, 4.0, -1.0, -1.0, 1.0]}, {"trial_id": 72074762, "stateRewards": [0.0, -1.0, -4.0, -4.0, -1.0, -4.0, 4.0]}, {"trial_id": 1587207, "stateRewards": [0.0, 4.0, 1.0, 6.0, 6.0, -1.0, -1.0]}, {"trial_id": 72488942, "stateRewards": [0.0, -4.0, 4.0, -1.0, -4.0, 4.0, -1.0]}, {"trial_id": 21727500, "stateRewards": [0.0, 1.0, -1.0, -1.0, 4.0, 1.0, -1.0]}, {"trial_id": 73701525, "stateRewards": [0.0, 1.0, 1.0, -4.0, -4.0, 4.0, -1.0]}, {"trial_id": 32833370, "stateRewards": [0.0, 1.0, -1.0, -1.0, -4.0, -4.0, 4.0]}, {"trial_id": 42436223, "stateRewards": [0.0, 1.0, -1.0, 1.0, 1.0, -6.0, -1.0]}, {"trial_id": 92498817, "stateRewards": [0.0, 6.0, 1.0, -1.0, -1.0, -1.0, 4.0]}, {"trial_id": 70406352, "stateRewards": [0.0, 1.0, -4.0, -4.0, 1.0, 4.0, -1.0]}, {"trial_id": 93101461, "stateRewards": [0.0, 1.0, 1.0, 4.0, 1.0, -6.0, 4.0]}, {"trial_id": 12999116, "stateRewards": [0.0, 4.0, -1.0, -1.0, -6.0, -6.0, 1.0]}, {"trial_id": 63684923, "stateRewards": [0.0, -1.0, 1.0, 4.0, 1.0, 4.0, -1.0]}, {"trial_id": 78589207, "stateRewards": [0.0, -1.0, -4.0, 4.0, -6.0, -1.0, 1.0]}, {"trial_id": 90058432, "stateRewards": [0.0, 1.0, 6.0, -4.0, 4.0, -4.0, -1.0]}, {"trial_id": 89117995, "stateRewards": [0.0, 1.0, 4.0, -4.0, 1.0, -4.0, 4.0]}, {"trial_id": 4204232, "stateRewards": [0.0, -4.0, -1.0, -1.0, -4.0, 1.0, 1.0]}, {"trial_id": 50767235, "stateRewards": [0.0, 1.0, 6.0, -4.0, -1.0, 1.0, 4.0]}, {"trial_id": 6285413, "stateRewards": [0.0, 4.0, 4.0, 1.0, -1.0, 1.0, 1.0]}, {"trial_id": 10044805, "stateRewards": [0.0, -6.0, 1.0, -1.0, -1.0, -1.0, 4.0]}, {"trial_id": 16683647, "stateRewards": [0.0, -1.0, 1.0, 1.0, 1.0, 4.0, -4.0]}, {"trial_id": 64938437, "stateRewards": [0.0, -4.0, 6.0, -4.0, 1.0, -4.0, 4.0]}, {"trial_id": 18516036, "stateRewards": [0.0, 1.0, -1.0, -4.0, -1.0, -1.0, -1.0]}, {"trial_id": 96903073, "stateRewards": [0.0, 1.0, 1.0, 4.0, -4.0, 1.0, -1.0]}, {"trial_id": 45003191, "stateRewards": [0.0, 4.0, -1.0, -4.0, -1.0, -1.0, 1.0]}, {"trial_id": 57220603, "stateRewards": [0.0, -4.0, 1.0, 1.0, -1.0, -1.0, 1.0]}, {"trial_id": 6267325, "stateRewards": [0.0, 1.0, -4.0, -1.0, -1.0, 1.0, 4.0]}, {"trial_id": 54513285, "stateRewards": [0.0, -6.0, 1.0, -1.0, -4.0, 1.0, -1.0]}, {"trial_id": 43589370, "stateRewards": [0.0, -4.0, 6.0, -1.0, 6.0, 1.0, -1.0]}, {"trial_id": 87099290, "stateRewards": [0.0, 1.0, -6.0, 1.0, -1.0, 1.0, -6.0]}, {"trial_id": 3851184, "stateRewards": [0.0, -4.0, -4.0, -1.0, 1.0, -1.0, 1.0]}, {"trial_id": 29164787, "stateRewards": [0.0, -4.0, -4.0, 1.0, -4.0, -4.0, 4.0]}, {"trial_id": 33487357, "stateRewards": [0.0, -4.0, -4.0, 1.0, -1.0, -1.0, -6.0]}, {"trial_id": 13627488, "stateRewards": [0.0, 1.0, 4.0, 1.0, 1.0, 4.0, -1.0]}, {"trial_id": 97471507, "stateRewards": [0.0, 6.0, 6.0, -4.0, -1.0, 4.0, -1.0]}, {"trial_id": 17347286, "stateRewards": [0.0, 1.0, -1.0, -4.0, 6.0, -1.0, 6.0]}, {"trial_id": 82101066, "stateRewards": [0.0, -1.0, 4.0, -1.0, -1.0, 1.0, -1.0]}, {"trial_id": 53789832, "stateRewards": [0.0, -4.0, 1.0, -1.0, -4.0, -6.0, -4.0]}, {"trial_id": 12946109, "stateRewards": [0.0, -1.0, -1.0, 1.0, -6.0, 4.0, -4.0]}, {"trial_id": 20802116, "stateRewards": [0.0, 1.0, 6.0, -4.0, 1.0, -1.0, 4.0]}, {"trial_id": 14979117, "stateRewards": [0.0, 1.0, 1.0, 1.0, 4.0, 6.0, -6.0]}, {"trial_id": 2923774, "stateRewards": [0.0, 1.0, -1.0, 4.0, 1.0, -1.0, 1.0]}, {"trial_id": 14223859, "stateRewards": [0.0, -1.0, -4.0, 1.0, -6.0, 1.0, 1.0]}, {"trial_id": 82672874, "stateRewards": [0.0, 4.0, 1.0, -1.0, 1.0, 1.0, 6.0]}, {"trial_id": 87742193, "stateRewards": [0.0, 4.0, 4.0, -1.0, -1.0, -6.0, 4.0]}, {"trial_id": 9112957, "stateRewards": [0.0, 1.0, 1.0, 4.0, -1.0, -4.0, -4.0]}, {"trial_id": 75889259, "stateRewards": [0.0, -1.0, -4.0, -6.0, -1.0, 4.0, 1.0]}, {"trial_id": 43143689, "stateRewards": [0.0, -1.0, 4.0, 1.0, 4.0, 1.0, -1.0]}, {"trial_id": 35163549, "stateRewards": [0.0, 1.0, -1.0, -1.0, 1.0, -1.0, 1.0]}, {"trial_id": 85440204, "stateRewards": [0.0, 4.0, 1.0, 4.0, 1.0, 4.0, -1.0]}, {"trial_id": 29735734, "stateRewards": [0.0, 4.0, 1.0, -1.0, 4.0, 1.0, 1.0]}, {"trial_id": 16238695, "stateRewards": [0.0, -1.0, -4.0, -1.0, -4.0, -6.0, 1.0]}, {"trial_id": 496280, "stateRewards": [0.0, 1.0, 1.0, 4.0, -4.0, -1.0, -1.0]}, {"trial_id": 78849959, "stateRewards": [0.0, -4.0, 1.0, 1.0, 1.0, 1.0, -1.0]}, {"trial_id": 5457498, "stateRewards": [0.0, -1.0, -6.0, 1.0, 1.0, -1.0, -1.0]}, {"trial_id": 29089191, "stateRewards": [0.0, 1.0, -6.0, 4.0, -1.0, -1.0, 4.0]}, {"trial_id": 62807543, "stateRewards": [0.0, -4.0, 1.0, 4.0, 1.0, 1.0, 4.0]}, {"trial_id": 16346387, "stateRewards": [0.0, -1.0, 4.0, 1.0, -1.0, -4.0, -1.0]}, {"trial_id": 97788841, "stateRewards": [0.0, 1.0, 1.0, 1.0, 4.0, 1.0, -4.0]}, {"trial_id": 69522964, "stateRewards": [0.0, -4.0, 6.0, 1.0, 1.0, -1.0, 1.0]}, {"trial_id": 59200005, "stateRewards": [0.0, 4.0, -1.0, -1.0, -1.0, -4.0, 4.0]}, {"trial_id": 46899136, "stateRewards": [0.0, 1.0, 4.0, 6.0, -1.0, 4.0, 4.0]}, {"trial_id": 34718479, "stateRewards": [0.0, -4.0, 4.0, 4.0, -1.0, -1.0, 4.0]}, {"trial_id": 39890983, "stateRewards": [0.0, -1.0, 6.0, 4.0, 1.0, 4.0, -1.0]}, {"trial_id": 21662898, "stateRewards": [0.0, -6.0, 6.0, -1.0, -4.0, -1.0, -1.0]}, {"trial_id": 15784205, "stateRewards": [0.0, -4.0, 1.0, 1.0, 1.0, -4.0, 1.0]}, {"trial_id": 45356726, "stateRewards": [0.0, -1.0, -1.0, -6.0, 1.0, 1.0, -1.0]}, {"trial_id": 20619130, "stateRewards": [0.0, -4.0, -4.0, 6.0, -4.0, -1.0, 6.0]}, {"trial_id": 73628537, "stateRewards": [0.0, -1.0, -4.0, -4.0, -1.0, -1.0, -4.0]}, {"trial_id": 33875771, "stateRewards": [0.0, 4.0, -1.0, -4.0, 1.0, 4.0, 1.0]}, {"trial_id": 182860, "stateRewards": [0.0, 4.0, -1.0, -1.0, 4.0, 1.0, -1.0]}, {"trial_id": 10780910, "stateRewards": [0.0, -6.0, 1.0, -6.0, -6.0, -4.0, -1.0]}, {"trial_id": 72120150, "stateRewards": [0.0, -4.0, 1.0, -1.0, 1.0, -1.0, 1.0]}, {"trial_id": 19950719, "stateRewards": [0.0, -4.0, 1.0, 1.0, 4.0, 4.0, -1.0]}, {"trial_id": 53220439, "stateRewards": [0.0, 1.0, -1.0, -1.0, -1.0, 6.0, -4.0]}, {"trial_id": 45245451, "stateRewards": [0.0, 1.0, -1.0, -1.0, -1.0, -1.0, 1.0]}, {"trial_id": 32421212, "stateRewards": [0.0, 1.0, 4.0, 1.0, 1.0, 1.0, -1.0]}, {"trial_id": 39408304, "stateRewards": [0.0, 6.0, 4.0, 1.0, -4.0, -1.0, -4.0]}, {"trial_id": 82498916, "stateRewards": [0.0, -4.0, -1.0, -1.0, -4.0, 1.0, -6.0]}, {"trial_id": 94409056, "stateRewards": [0.0, 4.0, -1.0, -1.0, 1.0, 1.0, 1.0]}, {"trial_id": 43161269, "stateRewards": [0.0, -4.0, 6.0, 1.0, -4.0, 1.0, 4.0]}, {"trial_id": 78287386, "stateRewards": [0.0, -1.0, -4.0, -1.0, 4.0, 4.0, -4.0]}, {"trial_id": 62439433, "stateRewards": [0.0, 1.0, -1.0, -1.0, -4.0, 1.0, -6.0]}, {"trial_id": 26001722, "stateRewards": [0.0, 6.0, -1.0, 1.0, 4.0, 1.0, -1.0]}, {"trial_id": 33155144, "stateRewards": [0.0, -4.0, -1.0, -4.0, -4.0, 1.0, 1.0]}, {"trial_id": 71337219, "stateRewards": [0.0, 1.0, -1.0, -1.0, 1.0, 1.0, 1.0]}, {"trial_id": 43373609, "stateRewards": [0.0, 1.0, -1.0, 4.0, 4.0, 6.0, -1.0]}, {"trial_id": 78724440, "stateRewards": [0.0, -6.0, -1.0, -4.0, 1.0, 1.0, 4.0]}, {"trial_id": 16880326, "stateRewards": [0.0, 6.0, -4.0, 6.0, 1.0, -4.0, 4.0]}, {"trial_id": 5848189, "stateRewards": [0.0, -6.0, 1.0, -1.0, 1.0, 1.0, 1.0]}, {"trial_id": 76441725, "stateRewards": [0.0, 6.0, 1.0, -1.0, 4.0, -4.0, 4.0]}, {"trial_id": 95757242, "stateRewards": [0.0, 4.0, 1.0, 4.0, 4.0, -1.0, 1.0]}, {"trial_id": 96216949, "stateRewards": [0.0, 6.0, 4.0, -4.0, -4.0, -1.0, 1.0]}, {"trial_id": 58680657, "stateRewards": [0.0, -4.0, 1.0, 6.0, 4.0, -4.0, 1.0]}, {"trial_id": 35802338, "stateRewards": [0.0, -4.0, 1.0, -1.0, 1.0, 4.0, -1.0]}, {"trial_id": 7636807, "stateRewards": [0.0, -1.0, 1.0, 1.0, 6.0, -1.0, 1.0]}, {"trial_id": 99229438, "stateRewards": [0.0, -1.0, 6.0, -1.0, -1.0, 1.0, 1.0]}, {"trial_id": 14811818, "stateRewards": [0.0, 1.0, -1.0, 1.0, -6.0, -1.0, 1.0]}, {"trial_id": 50662139, "stateRewards": [0.0, -1.0, -4.0, 1.0, -1.0, -1.0, 1.0]}, {"trial_id": 97216821, "stateRewards": [0.0, 4.0, 4.0, 1.0, -4.0, -4.0, -4.0]}, {"trial_id": 52917283, "stateRewards": [0.0, -1.0, 1.0, -1.0, -6.0, 1.0, -6.0]}, {"trial_id": 36985246, "stateRewards": [0.0, 4.0, 4.0, 4.0, -1.0, 1.0, 4.0]}, {"trial_id": 76271104, "stateRewards": [0.0, 4.0, -1.0, -1.0, -1.0, 4.0, -1.0]}, {"trial_id": 68955045, "stateRewards": [0.0, -4.0, 4.0, -1.0, -1.0, 6.0, -4.0]}, {"trial_id": 53273833, "stateRewards": [0.0, 1.0, 4.0, 1.0, -4.0, -1.0, -1.0]}, {"trial_id": 53401780, "stateRewards": [0.0, 1.0, 1.0, 4.0, -4.0, -4.0, -4.0]}, {"trial_id": 24067588, "stateRewards": [0.0, -1.0, 1.0, -4.0, -1.0, 6.0, -1.0]}, {"trial_id": 96929247, "stateRewards": [0.0, 4.0, 6.0, -4.0, 1.0, 6.0, -4.0]}, {"trial_id": 2913455, "stateRewards": [0.0, 4.0, 1.0, -4.0, -1.0, 1.0, -4.0]}, {"trial_id": 33489244, "stateRewards": [0.0, 1.0, -6.0, 6.0, 1.0, 4.0, 4.0]}, {"trial_id": 35163549, "stateRewards": [0.0, 1.0, -1.0, -1.0, 1.0, -1.0, 1.0]}, {"trial_id": 93543900, "stateRewards": [0.0, -1.0, -1.0, 4.0, 1.0, 6.0, 1.0]}, {"trial_id": 65560330, "stateRewards": [0.0, -4.0, 4.0, 6.0, 4.0, 1.0, -1.0]}, {"trial_id": 5627581, "stateRewards": [0.0, -1.0, -1.0, -1.0, 6.0, -1.0, -1.0]}, {"trial_id": 18411152, "stateRewards": [0.0, 1.0, 4.0, 4.0, 1.0, -4.0, 1.0]}, {"trial_id": 60956117, "stateRewards": [0.0, -1.0, 6.0, 1.0, -1.0, 6.0, 1.0]}, {"trial_id": 40678693, "stateRewards": [0.0, -4.0, -1.0, 1.0, 4.0, 4.0, 1.0]}, {"trial_id": 23313251, "stateRewards": [0.0, 1.0, 4.0, -1.0, -1.0, 4.0, -1.0]}, {"trial_id": 28376453, "stateRewards": [0.0, -1.0, -4.0, -4.0, -4.0, 4.0, -1.0]}, {"trial_id": 9905657, "stateRewards": [0.0, -1.0, -1.0, 1.0, 6.0, -4.0, -4.0]}, {"trial_id": 43109692, "stateRewards": [0.0, -4.0, -6.0, -1.0, 1.0, 4.0, -4.0]}, {"trial_id": 23130381, "stateRewards": [0.0, -1.0, -4.0, 4.0, -1.0, 4.0, 4.0]}, {"trial_id": 21642312, "stateRewards": [0.0, 6.0, 1.0, -1.0, -6.0, -1.0, -1.0]}, {"trial_id": 99123822, "stateRewards": [0.0, -1.0, -1.0, 4.0, 4.0, 4.0, -1.0]}, {"trial_id": 48105918, "stateRewards": [0.0, 4.0, -1.0, 1.0, 1.0, -1.0, -1.0]}, {"trial_id": 20451783, "stateRewards": [0.0, 4.0, -1.0, -1.0, -1.0, -1.0, -1.0]}, {"trial_id": 78206330, "stateRewards": [0.0, -1.0, -4.0, -4.0, 1.0, -1.0, -1.0]}, {"trial_id": 28928033, "stateRewards": [0.0, -4.0, -1.0, 1.0, -1.0, -1.0, 4.0]}, {"trial_id": 46806248, "stateRewards": [0.0, 1.0, 1.0, 4.0, -1.0, 1.0, 1.0]}, {"trial_id": 51091939, "stateRewards": [0.0, 1.0, -4.0, -6.0, -6.0, 1.0, -4.0]}, {"trial_id": 53250714, "stateRewards": [0.0, -1.0, 1.0, -4.0, 4.0, 4.0, -1.0]}, {"trial_id": 84958788, "stateRewards": [0.0, -1.0, 1.0, 1.0, -1.0, -1.0, -1.0]}, {"trial_id": 55767727, "stateRewards": [0.0, -1.0, -6.0, -4.0, -1.0, 4.0, -1.0]}, {"trial_id": 85774674, "stateRewards": [0.0, -4.0, 1.0, 1.0, -1.0, -1.0, -1.0]}, {"trial_id": 12912913, "stateRewards": [0.0, 1.0, 6.0, 1.0, -6.0, -1.0, 1.0]}, {"trial_id": 63279576, "stateRewards": [0.0, -4.0, 1.0, -4.0, 1.0, -1.0, 1.0]}, {"trial_id": 34154405, "stateRewards": [0.0, 4.0, 4.0, -1.0, -1.0, -1.0, -4.0]}, {"trial_id": 85144072, "stateRewards": [0.0, -6.0, -4.0, 1.0, 4.0, 6.0, -4.0]}, {"trial_id": 3865298, "stateRewards": [0.0, -1.0, -1.0, -4.0, 1.0, 1.0, -6.0]}, {"trial_id": 17321906, "stateRewards": [0.0, 4.0, -1.0, 1.0, 6.0, -4.0, -1.0]}, {"trial_id": 63900332, "stateRewards": [0.0, 1.0, -1.0, 4.0, -1.0, -6.0, -4.0]}, {"trial_id": 98110247, "stateRewards": [0.0, -1.0, 4.0, 6.0, 4.0, 1.0, 4.0]}, {"trial_id": 45840562, "stateRewards": [0.0, 1.0, 1.0, 1.0, 1.0, -1.0, -4.0]}, {"trial_id": 95242397, "stateRewards": [0.0, -4.0, 4.0, 4.0, 1.0, -1.0, -1.0]}, {"trial_id": 14317283, "stateRewards": [0.0, 4.0, -4.0, -4.0, -1.0, 4.0, -1.0]}, {"trial_id": 61413084, "stateRewards": [0.0, -1.0, 1.0, 6.0, -4.0, -1.0, -1.0]}, {"trial_id": 63885124, "stateRewards": [0.0, 1.0, 1.0, 4.0, 1.0, -6.0, 1.0]}, {"trial_id": 65485399, "stateRewards": [0.0, -4.0, 1.0, 1.0, -1.0, -1.0, -4.0]}, {"trial_id": 18952082, "stateRewards": [0.0, 1.0, 1.0, 6.0, 1.0, -1.0, 1.0]}, {"trial_id": 15305188, "stateRewards": [0.0, 1.0, -4.0, 1.0, -4.0, -1.0, 1.0]}, {"trial_id": 67220838, "stateRewards": [0.0, 1.0, -4.0, 1.0, -1.0, -1.0, 6.0]}, {"trial_id": 94140919, "stateRewards": [0.0, -4.0, 4.0, -4.0, 4.0, 4.0, -4.0]}, {"trial_id": 89783167, "stateRewards": [0.0, -4.0, -4.0, -1.0, 1.0, 4.0, -1.0]}, {"trial_id": 45296930, "stateRewards": [0.0, -1.0, 1.0, 4.0, -6.0, 1.0, -1.0]}, {"trial_id": 61232801, "stateRewards": [0.0, -1.0, -4.0, -4.0, 4.0, 1.0, 6.0]}, {"trial_id": 11667126, "stateRewards": [0.0, 4.0, -1.0, 1.0, -4.0, 1.0, -1.0]}, {"trial_id": 56776066, "stateRewards": [0.0, -4.0, 1.0, -4.0, 1.0, -4.0, 4.0]}, {"trial_id": 76876716, "stateRewards": [0.0, 4.0, -4.0, 1.0, -1.0, -1.0, -1.0]}, {"trial_id": 71337219, "stateRewards": [0.0, 1.0, -1.0, -1.0, 1.0, 1.0, 1.0]}, {"trial_id": 91461303, "stateRewards": [0.0, 4.0, -1.0, 1.0, -1.0, -1.0, -1.0]}, {"trial_id": 43516863, "stateRewards": [0.0, 1.0, 1.0, 1.0, -4.0, -4.0, 1.0]}, {"trial_id": 42289661, "stateRewards": [0.0, -6.0, 4.0, 1.0, -4.0, 6.0, 1.0]}, {"trial_id": 4875699, "stateRewards": [0.0, -1.0, 1.0, -1.0, -1.0, -1.0, 4.0]}, {"trial_id": 3481536, "stateRewards": [0.0, 1.0, 1.0, 6.0, 4.0, -1.0, -4.0]}, {"trial_id": 81911758, "stateRewards": [0.0, -1.0, 4.0, -4.0, -1.0, 4.0, 4.0]}, {"trial_id": 65012691, "stateRewards": [0.0, -6.0, -1.0, 1.0, 4.0, -4.0, 1.0]}, {"trial_id": 29260971, "stateRewards": [0.0, -1.0, 1.0, 1.0, 4.0, -1.0, 4.0]}, {"trial_id": 35427117, "stateRewards": [0.0, 1.0, -1.0, 4.0, 1.0, 1.0, -1.0]}, {"trial_id": 92470662, "stateRewards": [0.0, 1.0, 6.0, -1.0, 1.0, -1.0, -1.0]}, {"trial_id": 54140401, "stateRewards": [0.0, 1.0, -1.0, 1.0, 4.0, -4.0, 4.0]}, {"trial_id": 3481536, "stateRewards": [0.0, 1.0, 1.0, 6.0, 4.0, -1.0, -4.0]}, {"trial_id": 67164545, "stateRewards": [0.0, -4.0, 1.0, 1.0, 6.0, -1.0, -4.0]}, {"trial_id": 29813408, "stateRewards": [0.0, -1.0, 1.0, -1.0, -1.0, 1.0, -4.0]}, {"trial_id": 76270885, "stateRewards": [0.0, -1.0, -6.0, -6.0, -4.0, -1.0, 1.0]}, {"trial_id": 589767, "stateRewards": [0.0, -1.0, 4.0, 4.0, -1.0, -1.0, 6.0]}, {"trial_id": 64944520, "stateRewards": [0.0, 1.0, 4.0, -1.0, -1.0, -4.0, 6.0]}, {"trial_id": 73680099, "stateRewards": [0.0, 1.0, -6.0, 4.0, -4.0, -1.0, -1.0]}, {"trial_id": 26467204, "stateRewards": [0.0, 1.0, 1.0, 1.0, -1.0, -1.0, -1.0]}, {"trial_id": 55848218, "stateRewards": [0.0, 4.0, -1.0, -1.0, 4.0, 1.0, 6.0]}, {"trial_id": 26691274, "stateRewards": [0.0, -4.0, -1.0, -6.0, 1.0, -1.0, -4.0]}, {"trial_id": 31164437, "stateRewards": [0.0, 1.0, 4.0, -6.0, 1.0, -1.0, 1.0]}, {"trial_id": 19279439, "stateRewards": [0.0, -1.0, -1.0, -1.0, -4.0, 1.0, -1.0]}, {"trial_id": 37097918, "stateRewards": [0.0, 4.0, 4.0, -4.0, -1.0, 4.0, 4.0]}, {"trial_id": 25076558, "stateRewards": [0.0, -6.0, 1.0, -1.0, 4.0, -1.0, 1.0]}, {"trial_id": 45925750, "stateRewards": [0.0, -4.0, -1.0, 1.0, -6.0, -1.0, -1.0]}, {"trial_id": 69453608, "stateRewards": [0.0, -4.0, -1.0, -6.0, -1.0, -1.0, 4.0]}, {"trial_id": 14383182, "stateRewards": [0.0, -1.0, -1.0, -6.0, 4.0, -4.0, -4.0]}, {"trial_id": 31087380, "stateRewards": [0.0, 4.0, -1.0, 1.0, 4.0, 1.0, 1.0]}, {"trial_id": 99266287, "stateRewards": [0.0, 4.0, 4.0, -1.0, 4.0, 1.0, 6.0]}, {"trial_id": 50739460, "stateRewards": [0.0, 4.0, -1.0, -4.0, -6.0, -4.0, -4.0]}, {"trial_id": 14657181, "stateRewards": [0.0, 4.0, 1.0, -4.0, 1.0, -1.0, -6.0]}, {"trial_id": 52328625, "stateRewards": [0.0, -4.0, -1.0, -1.0, 4.0, -1.0, -4.0]}, {"trial_id": 79069543, "stateRewards": [0.0, -1.0, -1.0, -1.0, -1.0, 6.0, -4.0]}, {"trial_id": 29735734, "stateRewards": [0.0, 4.0, 1.0, -1.0, 4.0, 1.0, 1.0]}, {"trial_id": 17934679, "stateRewards": [0.0, 4.0, 1.0, -4.0, 1.0, -6.0, -1.0]}, {"trial_id": 32778090, "stateRewards": [0.0, -1.0, 6.0, -1.0, 4.0, -1.0, 4.0]}, {"trial_id": 61232801, "stateRewards": [0.0, -1.0, -4.0, -4.0, 4.0, 1.0, 6.0]}, {"trial_id": 27446299, "stateRewards": [0.0, -4.0, -6.0, 4.0, -1.0, 1.0, -1.0]}, {"trial_id": 98896751, "stateRewards": [0.0, 1.0, -4.0, -1.0, -1.0, -4.0, -4.0]}, {"trial_id": 47412475, "stateRewards": [0.0, -1.0, 1.0, -1.0, -1.0, -1.0, -1.0]}, {"trial_id": 36375361, "stateRewards": [0.0, 1.0, 6.0, 6.0, 4.0, 1.0, -1.0]}, {"trial_id": 54033351, "stateRewards": [0.0, 1.0, 1.0, 4.0, -1.0, 1.0, 4.0]}, {"trial_id": 57579745, "stateRewards": [0.0, 4.0, -1.0, -4.0, 4.0, 1.0, -1.0]}, {"trial_id": 58437824, "stateRewards": [0.0, -1.0, 4.0, 1.0, -1.0, 1.0, 1.0]}, {"trial_id": 67431589, "stateRewards": [0.0, -1.0, 1.0, -1.0, -1.0, -4.0, -4.0]}, {"trial_id": 71859176, "stateRewards": [0.0, -1.0, 1.0, 1.0, 1.0, -4.0, -4.0]}, {"trial_id": 52764904, "stateRewards": [0.0, -1.0, -6.0, 1.0, 4.0, 1.0, -1.0]}, {"trial_id": 91540005, "stateRewards": [0.0, 4.0, 1.0, 1.0, -1.0, -4.0, -1.0]}, {"trial_id": 85369960, "stateRewards": [0.0, -1.0, 1.0, -6.0, -1.0, 1.0, 1.0]}, {"trial_id": 52250350, "stateRewards": [0.0, 1.0, -4.0, 6.0, 4.0, -1.0, -4.0]}, {"trial_id": 83659131, "stateRewards": [0.0, 4.0, -1.0, -4.0, -1.0, 1.0, -1.0]}, {"trial_id": 20231262, "stateRewards": [0.0, 4.0, 1.0, 1.0, -4.0, -6.0, -1.0]}, {"trial_id": 86949888, "stateRewards": [0.0, -1.0, 1.0, 6.0, 4.0, -4.0, 4.0]}, {"trial_id": 90940912, "stateRewards": [0.0, -1.0, -1.0, -4.0, -6.0, 1.0, 1.0]}, {"trial_id": 98823007, "stateRewards": [0.0, 4.0, -4.0, 6.0, -1.0, 1.0, 4.0]}, {"trial_id": 87280287, "stateRewards": [0.0, -1.0, -4.0, -1.0, 1.0, -4.0, 1.0]}, {"trial_id": 11466506, "stateRewards": [0.0, -6.0, -1.0, -6.0, 1.0, -4.0, 1.0]}, {"trial_id": 49343299, "stateRewards": [0.0, 6.0, 1.0, -1.0, -1.0, -1.0, -6.0]}, {"trial_id": 13554804, "stateRewards": [0.0, -1.0, -4.0, -1.0, 4.0, -6.0, -1.0]}, {"trial_id": 3723685, "stateRewards": [0.0, 1.0, -1.0, 1.0, 1.0, 4.0, -1.0]}, {"trial_id": 99587283, "stateRewards": [0.0, -4.0, 1.0, 1.0, -1.0, -1.0, 4.0]}, {"trial_id": 54217119, "stateRewards": [0.0, -4.0, -1.0, -4.0, -1.0, 1.0, -1.0]}, {"trial_id": 33305699, "stateRewards": [0.0, -4.0, -4.0, -4.0, 1.0, -1.0, 4.0]}, {"trial_id": 88375583, "stateRewards": [0.0, -1.0, -4.0, 4.0, -1.0, 1.0, -1.0]}, {"trial_id": 92671561, "stateRewards": [0.0, -1.0, 1.0, 4.0, 4.0, -1.0, 4.0]}, {"trial_id": 96100031, "stateRewards": [0.0, 4.0, -1.0, -1.0, 6.0, 4.0, -6.0]}, {"trial_id": 18683870, "stateRewards": [0.0, -6.0, 1.0, -6.0, -4.0, -1.0, -6.0]}, {"trial_id": 41994394, "stateRewards": [0.0, 4.0, -1.0, 1.0, 1.0, -6.0, 1.0]}, {"trial_id": 46520792, "stateRewards": [0.0, 1.0, -1.0, -1.0, -4.0, -4.0, 1.0]}, {"trial_id": 75943457, "stateRewards": [0.0, -6.0, 6.0, -6.0, -1.0, -1.0, -1.0]}, {"trial_id": 15247761, "stateRewards": [0.0, -4.0, -4.0, -4.0, -6.0, -1.0, -1.0]}, {"trial_id": 93204554, "stateRewards": [0.0, 1.0, -4.0, 4.0, -1.0, 1.0, -1.0]}, {"trial_id": 66154303, "stateRewards": [0.0, -1.0, -6.0, 1.0, -4.0, 4.0, -4.0]}, {"trial_id": 98116681, "stateRewards": [0.0, -4.0, 4.0, 4.0, -1.0, -1.0, -1.0]}, {"trial_id": 58361493, "stateRewards": [0.0, -1.0, 4.0, -6.0, 1.0, 6.0, -1.0]}, {"trial_id": 65304799, "stateRewards": [0.0, 1.0, 4.0, -1.0, 1.0, 1.0, -4.0]}, {"trial_id": 81898678, "stateRewards": [0.0, 4.0, 1.0, -4.0, -1.0, -1.0, -1.0]}, {"trial_id": 22957734, "stateRewards": [0.0, -1.0, -4.0, 1.0, -1.0, -1.0, -1.0]}, {"trial_id": 11298734, "stateRewards": [0.0, -1.0, 1.0, 4.0, -6.0, 4.0, -4.0]}, {"trial_id": 24961105, "stateRewards": [0.0, -1.0, 1.0, -1.0, 1.0, -1.0, 4.0]}, {"trial_id": 68196983, "stateRewards": [0.0, -1.0, -1.0, -4.0, -1.0, 4.0, -1.0]}, {"trial_id": 35819248, "stateRewards": [0.0, 1.0, 1.0, -1.0, 4.0, -4.0, -1.0]}, {"trial_id": 14548885, "stateRewards": [0.0, -1.0, 4.0, -1.0, 1.0, 4.0, -1.0]}, {"trial_id": 13133434, "stateRewards": [0.0, -1.0, -1.0, -4.0, 4.0, 1.0, -1.0]}, {"trial_id": 17816436, "stateRewards": [0.0, -6.0, 1.0, 1.0, -4.0, -1.0, -1.0]}, {"trial_id": 37961308, "stateRewards": [0.0, 4.0, -4.0, -1.0, 1.0, 1.0, -1.0]}, {"trial_id": 11878859, "stateRewards": [0.0, -1.0, -1.0, -6.0, -6.0, -4.0, 4.0]}, {"trial_id": 74402535, "stateRewards": [0.0, -1.0, 1.0, -6.0, -1.0, 1.0, 6.0]}, {"trial_id": 20008993, "stateRewards": [0.0, -1.0, -1.0, -1.0, 4.0, 1.0, -1.0]}, {"trial_id": 59379825, "stateRewards": [0.0, 1.0, -1.0, 1.0, -1.0, -1.0, -6.0]}, {"trial_id": 420039, "stateRewards": [0.0, 4.0, -6.0, -1.0, -4.0, 1.0, -4.0]}, {"trial_id": 35302885, "stateRewards": [0.0, -1.0, -1.0, -4.0, 1.0, 4.0, 6.0]}, {"trial_id": 3568136, "stateRewards": [0.0, 4.0, -1.0, 4.0, -4.0, 1.0, -4.0]}, {"trial_id": 64990286, "stateRewards": [0.0, 4.0, 4.0, -1.0, 4.0, -6.0, -1.0]}, {"trial_id": 79620922, "stateRewards": [0.0, -1.0, -1.0, 4.0, 1.0, -1.0, 4.0]}, {"trial_id": 59398006, "stateRewards": [0.0, -1.0, -1.0, 4.0, -4.0, 1.0, -1.0]}, {"trial_id": 37021567, "stateRewards": [0.0, 1.0, 1.0, 1.0, -1.0, 4.0, -1.0]}, {"trial_id": 52924592, "stateRewards": [0.0, 6.0, -1.0, -1.0, -6.0, -1.0, -4.0]}, {"trial_id": 60746753, "stateRewards": [0.0, 4.0, -1.0, 1.0, 4.0, 1.0, -4.0]}, {"trial_id": 39971507, "stateRewards": [0.0, 1.0, 1.0, 1.0, 4.0, -1.0, 1.0]}, {"trial_id": 69504566, "stateRewards": [0.0, 1.0, -1.0, -1.0, -1.0, 1.0, 4.0]}, {"trial_id": 33267691, "stateRewards": [0.0, -6.0, -4.0, -4.0, 6.0, 4.0, -4.0]}, {"trial_id": 95993296, "stateRewards": [0.0, -1.0, 1.0, -4.0, 1.0, 1.0, 1.0]}, {"trial_id": 99826298, "stateRewards": [0.0, 4.0, 1.0, 1.0, 1.0, -4.0, -1.0]}, {"trial_id": 84870526, "stateRewards": [0.0, -4.0, -4.0, 1.0, -4.0, -1.0, 1.0]}, {"trial_id": 25007353, "stateRewards": [0.0, -1.0, 4.0, -1.0, 4.0, 6.0, -1.0]}, {"trial_id": 92747560, "stateRewards": [0.0, 4.0, -1.0, 1.0, 1.0, -4.0, 1.0]}, {"trial_id": 28764736, "stateRewards": [0.0, 4.0, 1.0, -1.0, 4.0, -1.0, 4.0]}, {"trial_id": 13153330, "stateRewards": [0.0, 6.0, -1.0, 6.0, 4.0, 1.0, 4.0]}, {"trial_id": 91663425, "stateRewards": [0.0, 1.0, -6.0, 4.0, 1.0, 1.0, -1.0]}, {"trial_id": 95332259, "stateRewards": [0.0, 1.0, 4.0, 4.0, -1.0, -1.0, -1.0]}, {"trial_id": 80418642, "stateRewards": [0.0, 4.0, -1.0, 4.0, 1.0, -4.0, -1.0]}, {"trial_id": 90997027, "stateRewards": [0.0, 1.0, -1.0, -1.0, 4.0, 4.0, 1.0]}, {"trial_id": 82329536, "stateRewards": [0.0, 4.0, -6.0, -1.0, 4.0, -4.0, 1.0]}, {"trial_id": 52321072, "stateRewards": [0.0, -4.0, 1.0, 4.0, -4.0, 1.0, 1.0]}, {"trial_id": 99095872, "stateRewards": [0.0, 4.0, 4.0, 1.0, -1.0, 1.0, -4.0]}, {"trial_id": 79823577, "stateRewards": [0.0, -6.0, 1.0, 1.0, 1.0, -1.0, 1.0]}, {"trial_id": 16346387, "stateRewards": [0.0, -1.0, 4.0, 1.0, -1.0, -4.0, -1.0]}, {"trial_id": 82983387, "stateRewards": [0.0, 1.0, -1.0, -4.0, 1.0, 1.0, 4.0]}, {"trial_id": 77444844, "stateRewards": [0.0, 1.0, -4.0, 1.0, 1.0, 1.0, -1.0]}, {"trial_id": 88813347, "stateRewards": [0.0, 6.0, -1.0, 1.0, 4.0, 4.0, 1.0]}, {"trial_id": 8788549, "stateRewards": [0.0, 6.0, 4.0, -4.0, -1.0, -6.0, -4.0]}, {"trial_id": 38122853, "stateRewards": [0.0, 1.0, 4.0, -1.0, 1.0, -1.0, 4.0]}, {"trial_id": 23927568, "stateRewards": [0.0, -1.0, 4.0, -6.0, 6.0, 1.0, 1.0]}, {"trial_id": 17808739, "stateRewards": [0.0, 4.0, -1.0, 4.0, 4.0, -4.0, -1.0]}, {"trial_id": 70498984, "stateRewards": [0.0, -1.0, 1.0, 1.0, -1.0, -1.0, 1.0]}, {"trial_id": 17892361, "stateRewards": [0.0, -4.0, 1.0, 1.0, 1.0, 1.0, 4.0]}, {"trial_id": 64719716, "stateRewards": [0.0, -1.0, 1.0, 1.0, 4.0, 4.0, 4.0]}, {"trial_id": 48826817, "stateRewards": [0.0, -4.0, 1.0, 4.0, 6.0, -4.0, 4.0]}, {"trial_id": 37889888, "stateRewards": [0.0, -1.0, -6.0, 1.0, -4.0, -1.0, -1.0]}, {"trial_id": 710408, "stateRewards": [0.0, 1.0, -6.0, 1.0, -1.0, 1.0, -4.0]}, {"trial_id": 61942293, "stateRewards": [0.0, 1.0, -6.0, 1.0, -4.0, -1.0, 1.0]}, {"trial_id": 23364183, "stateRewards": [0.0, 1.0, -1.0, -1.0, -4.0, 1.0, -1.0]}, {"trial_id": 18666252, "stateRewards": [0.0, 4.0, 1.0, 1.0, -1.0, -1.0, -4.0]}, {"trial_id": 81592976, "stateRewards": [0.0, -1.0, 1.0, 1.0, -1.0, 6.0, 1.0]}, {"trial_id": 8442500, "stateRewards": [0.0, -1.0, -6.0, -1.0, -4.0, -1.0, 1.0]}, {"trial_id": 84958788, "stateRewards": [0.0, -1.0, 1.0, 1.0, -1.0, -1.0, -1.0]}, {"trial_id": 66732111, "stateRewards": [0.0, -1.0, -6.0, 1.0, -1.0, -1.0, 1.0]}, {"trial_id": 68196983, "stateRewards": [0.0, -1.0, -1.0, -4.0, -1.0, 4.0, -1.0]}, {"trial_id": 33271024, "stateRewards": [0.0, 4.0, -1.0, -1.0, 4.0, 1.0, 1.0]}, {"trial_id": 26231504, "stateRewards": [0.0, -1.0, 1.0, -1.0, 4.0, -6.0, 1.0]}, {"trial_id": 20867001, "stateRewards": [0.0, -1.0, -4.0, 4.0, 1.0, -4.0, 1.0]}, {"trial_id": 13302732, "stateRewards": [0.0, -1.0, 1.0, -1.0, -1.0, -1.0, 1.0]}, {"trial_id": 2626381, "stateRewards": [0.0, -1.0, 4.0, -6.0, -1.0, -6.0, 1.0]}, {"trial_id": 87522482, "stateRewards": [0.0, -6.0, -1.0, 1.0, 4.0, -4.0, 4.0]}, {"trial_id": 18929292, "stateRewards": [0.0, -1.0, 1.0, -1.0, 4.0, -1.0, -4.0]}, {"trial_id": 25107992, "stateRewards": [0.0, -6.0, -4.0, 1.0, -4.0, 4.0, -4.0]}, {"trial_id": 48682669, "stateRewards": [0.0, -4.0, 1.0, 4.0, -1.0, -4.0, -1.0]}, {"trial_id": 20022425, "stateRewards": [0.0, -4.0, 4.0, -1.0, -6.0, -1.0, -4.0]}, {"trial_id": 63814347, "stateRewards": [0.0, -4.0, 1.0, -4.0, 1.0, 4.0, -1.0]}, {"trial_id": 63991241, "stateRewards": [0.0, -1.0, 1.0, -1.0, -1.0, -1.0, -4.0]}, {"trial_id": 21670836, "stateRewards": [0.0, 6.0, -6.0, 1.0, -4.0, -4.0, 1.0]}, {"trial_id": 51944481, "stateRewards": [0.0, 4.0, 6.0, 4.0, 1.0, 1.0, 1.0]}, {"trial_id": 61858239, "stateRewards": [0.0, -1.0, 1.0, 1.0, 4.0, 4.0, 1.0]}, {"trial_id": 31559131, "stateRewards": [0.0, -4.0, 4.0, -4.0, 1.0, -6.0, 4.0]}, {"trial_id": 34203279, "stateRewards": [0.0, -1.0, 4.0, 4.0, -1.0, -4.0, 1.0]}, {"trial_id": 63144790, "stateRewards": [0.0, 1.0, -1.0, -1.0, -4.0, 4.0, -1.0]}, {"trial_id": 22351455, "stateRewards": [0.0, 1.0, 1.0, 6.0, -1.0, 1.0, -1.0]}, {"trial_id": 70549664, "stateRewards": [0.0, 1.0, -1.0, 4.0, -4.0, 1.0, 1.0]}, {"trial_id": 56383678, "stateRewards": [0.0, 4.0, -1.0, -1.0, -4.0, -1.0, 1.0]}, {"trial_id": 37220340, "stateRewards": [0.0, -1.0, -1.0, 4.0, -1.0, 4.0, -4.0]}, {"trial_id": 89053197, "stateRewards": [0.0, 1.0, 4.0, 1.0, -4.0, 1.0, -1.0]}, {"trial_id": 25548885, "stateRewards": [0.0, -4.0, 4.0, 1.0, 1.0, 4.0, 4.0]}, {"trial_id": 26599268, "stateRewards": [0.0, 1.0, 1.0, 6.0, -6.0, -1.0, 1.0]}, {"trial_id": 42507155, "stateRewards": [0.0, 1.0, -1.0, 1.0, -1.0, 4.0, -4.0]}, {"trial_id": 30106456, "stateRewards": [0.0, -4.0, -4.0, 4.0, 4.0, 1.0, 1.0]}, {"trial_id": 18709378, "stateRewards": [0.0, 4.0, -1.0, -4.0, 4.0, 4.0, -1.0]}, {"trial_id": 3310432, "stateRewards": [0.0, 1.0, -1.0, 1.0, 6.0, -4.0, -1.0]}, {"trial_id": 24300614, "stateRewards": [0.0, 4.0, -4.0, -4.0, 1.0, -4.0, -1.0]}, {"trial_id": 23938410, "stateRewards": [0.0, -6.0, -1.0, -1.0, 1.0, 6.0, -6.0]}, {"trial_id": 34890047, "stateRewards": [0.0, 4.0, -1.0, -1.0, -4.0, -6.0, -1.0]}, {"trial_id": 75534717, "stateRewards": [0.0, -1.0, 1.0, -6.0, -1.0, 1.0, -1.0]}, {"trial_id": 83860852, "stateRewards": [0.0, -1.0, 4.0, -6.0, 1.0, -1.0, 4.0]}, {"trial_id": 44554402, "stateRewards": [0.0, -1.0, 1.0, -1.0, 1.0, 4.0, -4.0]}, {"trial_id": 29867564, "stateRewards": [0.0, 4.0, 4.0, -4.0, 1.0, 4.0, 1.0]}, {"trial_id": 61089193, "stateRewards": [0.0, 4.0, 1.0, -4.0, -1.0, -4.0, 6.0]}, {"trial_id": 45899565, "stateRewards": [0.0, 1.0, -1.0, 6.0, -1.0, -4.0, 1.0]}, {"trial_id": 80598980, "stateRewards": [0.0, -6.0, -4.0, 1.0, 1.0, 4.0, 1.0]}, {"trial_id": 67457794, "stateRewards": [0.0, 1.0, 6.0, -4.0, -1.0, 4.0, -4.0]}, {"trial_id": 22829802, "stateRewards": [0.0, -4.0, 1.0, 4.0, 1.0, -1.0, -1.0]}, {"trial_id": 52849513, "stateRewards": [0.0, -6.0, 6.0, -4.0, -4.0, -4.0, 4.0]}, {"trial_id": 52665167, "stateRewards": [0.0, 1.0, -4.0, -4.0, 4.0, 1.0, -1.0]}, {"trial_id": 40887553, "stateRewards": [0.0, -4.0, 4.0, 1.0, 4.0, 4.0, -1.0]}, {"trial_id": 89152415, "stateRewards": [0.0, 4.0, 1.0, 1.0, -4.0, -4.0, 1.0]}, {"trial_id": 85261524, "stateRewards": [0.0, -4.0, -1.0, 4.0, -1.0, -6.0, -6.0]}, {"trial_id": 57388947, "stateRewards": [0.0, 1.0, 1.0, -4.0, 6.0, 4.0, -1.0]}, {"trial_id": 80432240, "stateRewards": [0.0, -1.0, 1.0, 1.0, 1.0, -4.0, 4.0]}, {"trial_id": 88144192, "stateRewards": [0.0, 6.0, -1.0, 1.0, 4.0, -1.0, -1.0]}, {"trial_id": 16426420, "stateRewards": [0.0, 1.0, -1.0, 1.0, -4.0, -4.0, -1.0]}, {"trial_id": 27450567, "stateRewards": [0.0, 1.0, -1.0, 1.0, -4.0, 6.0, -6.0]}, {"trial_id": 5647535, "stateRewards": [0.0, 4.0, 1.0, -1.0, -1.0, 1.0, 6.0]}, {"trial_id": 86610470, "stateRewards": [0.0, -4.0, 4.0, 4.0, 1.0, 4.0, -4.0]}, {"trial_id": 65485399, "stateRewards": [0.0, -4.0, 1.0, 1.0, -1.0, -1.0, -4.0]}, {"trial_id": 17867369, "stateRewards": [0.0, -1.0, -1.0, -1.0, 4.0, 1.0, 1.0]}, {"trial_id": 27198462, "stateRewards": [0.0, 1.0, -1.0, 1.0, 4.0, -1.0, 1.0]}, {"trial_id": 40774753, "stateRewards": [0.0, -1.0, -4.0, -6.0, 4.0, 1.0, 4.0]}, {"trial_id": 51767144, "stateRewards": [0.0, -1.0, -4.0, -4.0, 6.0, 1.0, 4.0]}, {"trial_id": 46073666, "stateRewards": [0.0, 4.0, 1.0, -1.0, -4.0, 1.0, -6.0]}, {"trial_id": 2732381, "stateRewards": [0.0, 1.0, 1.0, 4.0, -4.0, 1.0, 1.0]}, {"trial_id": 11001118, "stateRewards": [0.0, 4.0, 6.0, 1.0, 6.0, 4.0, 4.0]}, {"trial_id": 26768254, "stateRewards": [0.0, -4.0, 1.0, -6.0, 4.0, -1.0, 1.0]}, {"trial_id": 41093480, "stateRewards": [0.0, 4.0, 1.0, -1.0, -4.0, 1.0, -1.0]}, {"trial_id": 53521855, "stateRewards": [0.0, -1.0, -1.0, -4.0, -4.0, 1.0, 4.0]}, {"trial_id": 30273964, "stateRewards": [0.0, -1.0, 1.0, 6.0, -4.0, 1.0, 1.0]}, {"trial_id": 79226367, "stateRewards": [0.0, -4.0, -1.0, 6.0, -1.0, -1.0, -1.0]}, {"trial_id": 57598485, "stateRewards": [0.0, 4.0, -6.0, -4.0, 1.0, 1.0, -1.0]}, {"trial_id": 83436022, "stateRewards": [0.0, 4.0, -4.0, 4.0, -4.0, 1.0, 1.0]}, {"trial_id": 24456092, "stateRewards": [0.0, 4.0, -4.0, 4.0, -6.0, 4.0, 1.0]}, {"trial_id": 97139781, "stateRewards": [0.0, 1.0, -1.0, 4.0, 1.0, -4.0, 1.0]}, {"trial_id": 92867121, "stateRewards": [0.0, 1.0, -1.0, 6.0, 4.0, -1.0, 4.0]}, {"trial_id": 50973456, "stateRewards": [0.0, 1.0, 4.0, -1.0, 1.0, 4.0, 1.0]}, {"trial_id": 63699012, "stateRewards": [0.0, -4.0, 6.0, -4.0, 1.0, -6.0, -1.0]}, {"trial_id": 73936298, "stateRewards": [0.0, -6.0, 4.0, -1.0, 4.0, -4.0, 1.0]}, {"trial_id": 30499722, "stateRewards": [0.0, -6.0, -4.0, 1.0, 6.0, -1.0, -1.0]}, {"trial_id": 73839955, "stateRewards": [0.0, -4.0, 1.0, 1.0, -6.0, 4.0, -1.0]}, {"trial_id": 7354914, "stateRewards": [0.0, 4.0, 1.0, -1.0, -4.0, -1.0, -1.0]}, {"trial_id": 23355037, "stateRewards": [0.0, 1.0, 1.0, -4.0, -1.0, -1.0, 1.0]}, {"trial_id": 36588128, "stateRewards": [0.0, 1.0, -1.0, 1.0, 1.0, 1.0, -1.0]}, {"trial_id": 68125399, "stateRewards": [0.0, 1.0, 1.0, -6.0, 6.0, 1.0, 1.0]}, {"trial_id": 21291407, "stateRewards": [0.0, 4.0, 4.0, 1.0, 4.0, -4.0, -4.0]}, {"trial_id": 68441519, "stateRewards": [0.0, 1.0, -4.0, -1.0, 1.0, 4.0, 4.0]}, {"trial_id": 22286398, "stateRewards": [0.0, 4.0, -6.0, -4.0, 1.0, -6.0, 4.0]}, {"trial_id": 20330418, "stateRewards": [0.0, -1.0, -1.0, -6.0, 1.0, -1.0, -1.0]}, {"trial_id": 48606551, "stateRewards": [0.0, -1.0, -6.0, -4.0, -4.0, 4.0, 1.0]}, {"trial_id": 20514962, "stateRewards": [0.0, 1.0, -6.0, 1.0, -4.0, 1.0, 1.0]}, {"trial_id": 78485480, "stateRewards": [0.0, 4.0, 1.0, -4.0, -6.0, -4.0, -1.0]}, {"trial_id": 10448546, "stateRewards": [0.0, -1.0, -1.0, -1.0, -4.0, -1.0, 4.0]}, {"trial_id": 76410829, "stateRewards": [0.0, -1.0, 1.0, 1.0, -6.0, -1.0, -4.0]}, {"trial_id": 67800550, "stateRewards": [0.0, 1.0, 1.0, -6.0, 1.0, -4.0, -1.0]}, {"trial_id": 4892018, "stateRewards": [0.0, -1.0, 1.0, 4.0, -4.0, -4.0, 1.0]}, {"trial_id": 93033817, "stateRewards": [0.0, -1.0, -4.0, -4.0, 4.0, 4.0, 1.0]}, {"trial_id": 75335950, "stateRewards": [0.0, -1.0, 1.0, 4.0, 4.0, -4.0, 4.0]}, {"trial_id": 17352909, "stateRewards": [0.0, -4.0, -1.0, 1.0, -4.0, -4.0, 1.0]}, {"trial_id": 63022668, "stateRewards": [0.0, 1.0, 1.0, 1.0, -4.0, 4.0, 4.0]}, {"trial_id": 59428322, "stateRewards": [0.0, 4.0, -4.0, 4.0, -1.0, 1.0, 1.0]}, {"trial_id": 43779641, "stateRewards": [0.0, 1.0, 1.0, -1.0, -1.0, -1.0, -1.0]}, {"trial_id": 42866918, "stateRewards": [0.0, 4.0, 4.0, -1.0, 1.0, -1.0, -4.0]}, {"trial_id": 1023452, "stateRewards": [0.0, 4.0, -1.0, -4.0, 1.0, -1.0, 1.0]}, {"trial_id": 31703215, "stateRewards": [0.0, 4.0, -6.0, -1.0, -4.0, 1.0, -1.0]}, {"trial_id": 96162090, "stateRewards": [0.0, 1.0, -4.0, -4.0, -4.0, -1.0, 4.0]}, {"trial_id": 92262368, "stateRewards": [0.0, -4.0, 4.0, 6.0, -1.0, -4.0, 1.0]}, {"trial_id": 90603719, "stateRewards": [0.0, -1.0, -4.0, 1.0, -6.0, -1.0, 1.0]}, {"trial_id": 9879163, "stateRewards": [0.0, 1.0, 4.0, 1.0, 1.0, -4.0, -6.0]}, {"trial_id": 92592354, "stateRewards": [0.0, -4.0, 1.0, -1.0, -1.0, -4.0, -1.0]}, {"trial_id": 30509323, "stateRewards": [0.0, -4.0, 4.0, -6.0, 1.0, 1.0, -4.0]}, {"trial_id": 8517838, "stateRewards": [0.0, -1.0, -4.0, -4.0, -4.0, -6.0, -1.0]}, {"trial_id": 46338225, "stateRewards": [0.0, 1.0, -1.0, 6.0, 4.0, 1.0, -1.0]}, {"trial_id": 62573448, "stateRewards": [0.0, 1.0, 6.0, -1.0, -1.0, -1.0, -1.0]}, {"trial_id": 32350903, "stateRewards": [0.0, -1.0, -1.0, 1.0, -1.0, 4.0, 1.0]}, {"trial_id": 24205135, "stateRewards": [0.0, 6.0, -4.0, 1.0, 4.0, 1.0, -4.0]}, {"trial_id": 57869415, "stateRewards": [0.0, 4.0, 6.0, 4.0, 1.0, -1.0, 1.0]}, {"trial_id": 57784334, "stateRewards": [0.0, -4.0, 1.0, 4.0, 4.0, 1.0, -1.0]}, {"trial_id": 80711783, "stateRewards": [0.0, 1.0, -1.0, -4.0, -1.0, -4.0, -1.0]}, {"trial_id": 10285312, "stateRewards": [0.0, 4.0, 1.0, -1.0, 4.0, 4.0, 6.0]}, {"trial_id": 17686429, "stateRewards": [0.0, 6.0, 1.0, -4.0, 4.0, -4.0, 1.0]}, {"trial_id": 24985331, "stateRewards": [0.0, -6.0, 1.0, -1.0, -4.0, -4.0, -1.0]}, {"trial_id": 52090739, "stateRewards": [0.0, 4.0, -4.0, -4.0, 1.0, 4.0, -4.0]}, {"trial_id": 34847811, "stateRewards": [0.0, -1.0, -6.0, -1.0, 4.0, 1.0, 4.0]}, {"trial_id": 58719840, "stateRewards": [0.0, -6.0, 1.0, 6.0, 6.0, 4.0, -4.0]}, {"trial_id": 46380144, "stateRewards": [0.0, 6.0, -1.0, -1.0, 4.0, -1.0, 4.0]}, {"trial_id": 32364926, "stateRewards": [0.0, 1.0, 1.0, 4.0, 1.0, 1.0, 4.0]}, {"trial_id": 55311471, "stateRewards": [0.0, -4.0, -4.0, -4.0, -1.0, -1.0, 4.0]}, {"trial_id": 76223759, "stateRewards": [0.0, -4.0, -1.0, -1.0, -1.0, 1.0, 1.0]}, {"trial_id": 30840376, "stateRewards": [0.0, -4.0, -1.0, 4.0, 1.0, 1.0, -1.0]}, {"trial_id": 19898142, "stateRewards": [0.0, -4.0, 1.0, -4.0, -1.0, -4.0, 6.0]}, {"trial_id": 66769201, "stateRewards": [0.0, -6.0, 1.0, 1.0, 4.0, 1.0, 1.0]}, {"trial_id": 9693185, "stateRewards": [0.0, 4.0, 1.0, 1.0, 1.0, -1.0, 4.0]}, {"trial_id": 13687686, "stateRewards": [0.0, 1.0, 4.0, -1.0, 1.0, 6.0, -1.0]}, {"trial_id": 76632142, "stateRewards": [0.0, 1.0, -4.0, -6.0, 1.0, -4.0, 4.0]}, {"trial_id": 42028136, "stateRewards": [0.0, 1.0, 4.0, 1.0, -1.0, 1.0, 1.0]}, {"trial_id": 89731090, "stateRewards": [0.0, -4.0, 1.0, -6.0, 6.0, -6.0, -1.0]}, {"trial_id": 25795493, "stateRewards": [0.0, -1.0, 1.0, -1.0, -6.0, 1.0, 1.0]}, {"trial_id": 10858486, "stateRewards": [0.0, 4.0, -1.0, -4.0, 6.0, -4.0, -1.0]}, {"trial_id": 26624888, "stateRewards": [0.0, -1.0, 1.0, 4.0, 6.0, 1.0, -6.0]}, {"trial_id": 50449438, "stateRewards": [0.0, -6.0, -1.0, -4.0, -1.0, -6.0, 1.0]}, {"trial_id": 91971228, "stateRewards": [0.0, 4.0, 6.0, -1.0, -1.0, -4.0, -1.0]}, {"trial_id": 82983387, "stateRewards": [0.0, 1.0, -1.0, -4.0, 1.0, 1.0, 4.0]}, {"trial_id": 61374146, "stateRewards": [0.0, -4.0, -6.0, 4.0, 1.0, -1.0, 6.0]}, {"trial_id": 78582333, "stateRewards": [0.0, 1.0, -1.0, 1.0, 6.0, -1.0, 1.0]}, {"trial_id": 45419242, "stateRewards": [0.0, -4.0, 4.0, 4.0, -6.0, 1.0, 4.0]}, {"trial_id": 57407771, "stateRewards": [0.0, 4.0, 4.0, -4.0, -1.0, 6.0, -4.0]}, {"trial_id": 17952916, "stateRewards": [0.0, 4.0, -1.0, 6.0, 1.0, 1.0, -1.0]}, {"trial_id": 69643080, "stateRewards": [0.0, 1.0, 4.0, -1.0, 1.0, 1.0, -1.0]}, {"trial_id": 67800550, "stateRewards": [0.0, 1.0, 1.0, -6.0, 1.0, -4.0, -1.0]}, {"trial_id": 78463256, "stateRewards": [0.0, 1.0, 4.0, 4.0, -1.0, -1.0, -4.0]}, {"trial_id": 16815728, "stateRewards": [0.0, 4.0, 4.0, 1.0, 4.0, -1.0, 1.0]}, {"trial_id": 21858064, "stateRewards": [0.0, 6.0, 4.0, -1.0, -4.0, 1.0, 4.0]}]